{
  "format": "g2b_opencrab_github_json_evidence_shard_v2_50_rows",
  "dataset": "g2b-public-procurement-9space-1500n-25mb-v1",
  "layout": "flat-root-json-50-rows-per-file",
  "shard_index": 95,
  "item_start_1based": 4701,
  "item_end_1based": 4750,
  "items_in_shard": 50,
  "total_items_all_shards": 10001,
  "items": [
    {
      "source_line": 4701,
      "chunk_id": "chunk:g2b:sentence:f22088cd9d397e002667f535",
      "evidence_id": "evidence:g2b:sentence:row:bdf04ee877cda594dbcc33c7",
      "document_id": "doc:g2b:source:7b163281f6da85630a69aafe",
      "service": "backfill_hrcsp_ssstndrd_info",
      "operation": "getPublicPrcureThngInfoThng",
      "source_file": "backfill_hrcsp_ssstndrd_info/raw/getPublicPrcureThngInfoThng/2025-06/page_00001.json",
      "text": "G2B public OpenAPI row. service=backfill_hrcsp_ssstndrd_info. operation=getPublicPrcureThngInfoThng. source_file=raw/getPublicPrcureThngInfoThng/2025-06/page_00001.json. row_index=31. bfSpecRgstNo=R25BD00075552; prdctClsfcNoNm=고무판 등 8종 구매; rlDminsttNm=해군군수사령부; asignBdgtAmt=37522530; bsnsDivNm=물품; dlvrDaynum=0; opninRgstClseDt=2025-06-04 00:00:00; orderInsttNm=해군군수사령부; prdctDtlList=[1^^고무판 등 8종 구매]; rcptDt=2025-06-02 09:55:01; refNo=PS2025SCF22341; rgstDt=2025-06-02 09:55:01; swBizObjYn=N.",
      "hash": "sha256:79b4ee428e047ab94f8044657d692faf09324c26c1a7258b5ffd552b64dbeeaf",
      "source_path": "backfill_hrcsp_ssstndrd_info/raw/getPublicPrcureThngInfoThng/2025-06/page_00001.json",
      "opencrab_probe_marker": "OPENCRAB_JSON_50_SHARD_095_FIRST_ROW_04701"
    },
    {
      "source_line": 4702,
      "chunk_id": "chunk:g2b:sentence:f977ac8f79554c58f4395651",
      "evidence_id": "evidence:g2b:sentence:row:514724fcf03e956d92026d81",
      "document_id": "doc:g2b:source:7b163281f6da85630a69aafe",
      "service": "backfill_hrcsp_ssstndrd_info",
      "operation": "getPublicPrcureThngInfoThng",
      "source_file": "backfill_hrcsp_ssstndrd_info/raw/getPublicPrcureThngInfoThng/2025-06/page_00001.json",
      "text": "G2B public OpenAPI row. service=backfill_hrcsp_ssstndrd_info. operation=getPublicPrcureThngInfoThng. source_file=raw/getPublicPrcureThngInfoThng/2025-06/page_00001.json. row_index=32. bfSpecRgstNo=R25BD00075555; bidNtceNoList=R25BK00898398,R25BK00928042; ofclNm=정윤호; ofclTelNo=070-4056-7171; prdctClsfcNoNm=행복도시 연결도로 회덕IC 신설공사 아스콘 구매 ; rlDminsttNm=한국도로공사 남부도로개량사업단; asignBdgtAmt=1838097270; bsnsDivNm=물품; chgDt=2025-06-02 09:58:55; dlvrDaynum=0; dlvrTmlmtDt=2026-05-31 00:00:00; opninRgstClseDt=2025-06-08 23:59:00; orderInsttNm=조달청 대전지방조달청; prdctDtlList=[1^3011159701^아스팔트콘크리트],[2^3011159701^아스팔트콘크리트],[3^3011159701^아스팔트콘크리트]; rcptDt=2025-06-02 09:58:55; refNo=공사관리1부-566; rgstDt=2025-06-02 09:58:52; specDocFileUrl1=https://www.g2b.go.kr/pn/pnz/pnza/UntyAtchFile/downloadFile.do?bfSpecRegNo=R25BD00075555&fileType=BFDTL&fileSeq=1; specDocFileUrl2=https://www.g2b.go.kr/pn/pnz/pnza/UntyAtchFile/downloadFile.do?bfSpecRegNo=R25BD00075555&fileType=BFDTL&fileSeq=2; specDocFileUrl3=https://www.g2b.go.kr/pn/pnz/pnza/UntyAtchFile/downloadFile.do?bfSpecRegNo=R25BD00075555&fileType=BFDTL&fileSeq=3; specDocFileUrl4=https://www.g2b.go.kr/pn/pnz/pnza/UntyAtchFile/downloadFile.do?bfSpecRegNo=R25BD00075555&fileType=BFDTL&fileSeq=4; swBizObjYn=N.",
      "hash": "sha256:7966c9383620b667a35d9fa84c357b6ddf569102e3841d8fbe9204b492a59227",
      "source_path": "backfill_hrcsp_ssstndrd_info/raw/getPublicPrcureThngInfoThng/2025-06/page_00001.json"
    },
    {
      "source_line": 4703,
      "chunk_id": "chunk:g2b:sentence:e7a4bcfec4cc906bd2b94d9c",
      "evidence_id": "evidence:g2b:sentence:row:9b8086ccff801367d38e7dec",
      "document_id": "doc:g2b:source:7b163281f6da85630a69aafe",
      "service": "backfill_hrcsp_ssstndrd_info",
      "operation": "getPublicPrcureThngInfoThng",
      "source_file": "backfill_hrcsp_ssstndrd_info/raw/getPublicPrcureThngInfoThng/2025-06/page_00001.json",
      "text": "G2B public OpenAPI row. service=backfill_hrcsp_ssstndrd_info. operation=getPublicPrcureThngInfoThng. source_file=raw/getPublicPrcureThngInfoThng/2025-06/page_00001.json. row_index=33. bfSpecRgstNo=R25BD00075557; bidNtceNoList=R25BK00914605; ofclNm=이기운; ofclTelNo=070-4056-8262; prdctClsfcNoNm=영산강 강변도로 개설공사(2-2단계) 1공구 ICP 말뚝 구매; rlDminsttNm=전라남도; asignBdgtAmt=349390500; bsnsDivNm=물품; chgDt=2025-06-02 10:00:29; dlvrDaynum=0; dlvrTmlmtDt=2025-12-10 00:00:00; opninRgstClseDt=2025-06-07 23:59:00; orderInsttNm=조달청 광주지방조달청; prdctDtlList=[1^3010280201^콘크리트파일],[2^3010280201^콘크리트파일],[3^3010280201^콘크리트파일],[4^3010280201^콘크리트파일],[5^3010280201^콘크리트파일],[6^3010280201^콘크리트파일]; rcptDt=2025-06-02 10:00:29; refNo=도로정책과-3925; rgstDt=2025-06-02 10:00:27; specDocFileUrl1=https://www.g2b.go.kr/pn/pnz/pnza/UntyAtchFile/downloadFile.do?bfSpecRegNo=R25BD00075557&fileType=BFDTL&fileSeq=1; swBizObjYn=N.",
      "hash": "sha256:525f677d5fa1f0117ffa866c45fea1dc11d3ffc9e36efceaf3e6b12e9e5ee467",
      "source_path": "backfill_hrcsp_ssstndrd_info/raw/getPublicPrcureThngInfoThng/2025-06/page_00001.json"
    },
    {
      "source_line": 4704,
      "chunk_id": "chunk:g2b:sentence:b5a1b64a361df36ebea30b5c",
      "evidence_id": "evidence:g2b:sentence:row:22900e9ece9d3b042b9912a2",
      "document_id": "doc:g2b:source:7b163281f6da85630a69aafe",
      "service": "backfill_hrcsp_ssstndrd_info",
      "operation": "getPublicPrcureThngInfoThng",
      "source_file": "backfill_hrcsp_ssstndrd_info/raw/getPublicPrcureThngInfoThng/2025-06/page_00001.json",
      "text": "G2B public OpenAPI row. service=backfill_hrcsp_ssstndrd_info. operation=getPublicPrcureThngInfoThng. source_file=raw/getPublicPrcureThngInfoThng/2025-06/page_00001.json. row_index=34. bfSpecRgstNo=R25BD00075558; ofclNm=김지훈; ofclTelNo=070-4056-8923; prdctClsfcNoNm=산학융합 PLAZA 신축공사(건축 관급) 타일류; rlDminsttNm=전북대학교; asignBdgtAmt=121435680; bsnsDivNm=물품; chgDt=2025-06-02 10:02:11; dlvrDaynum=100; opninRgstClseDt=2025-06-09 23:59:00; orderInsttNm=조달청 전북지방조달청; prdctDtlList=[1^3013170401^도기질타일]; rcptDt=2025-06-02 10:02:11; refNo=시설과-5586; rgstDt=2025-06-02 10:02:08; specDocFileUrl1=https://www.g2b.go.kr/pn/pnz/pnza/UntyAtchFile/downloadFile.do?bfSpecRegNo=R25BD00075558&fileType=BFDTL&fileSeq=1; specDocFileUrl2=https://www.g2b.go.kr/pn/pnz/pnza/UntyAtchFile/downloadFile.do?bfSpecRegNo=R25BD00075558&fileType=BFDTL&fileSeq=2; swBizObjYn=N.",
      "hash": "sha256:ad222273904cd63b97320e19665f2b2c7e5f6f2308f7e23c9cbd9742b0cec600",
      "source_path": "backfill_hrcsp_ssstndrd_info/raw/getPublicPrcureThngInfoThng/2025-06/page_00001.json"
    },
    {
      "source_line": 4705,
      "chunk_id": "chunk:g2b:sentence:c7f68bc8977543a21fe71e80",
      "evidence_id": "evidence:g2b:sentence:row:72fe0ee3b69452ca419b8632",
      "document_id": "doc:g2b:source:7b163281f6da85630a69aafe",
      "service": "backfill_hrcsp_ssstndrd_info",
      "operation": "getPublicPrcureThngInfoThng",
      "source_file": "backfill_hrcsp_ssstndrd_info/raw/getPublicPrcureThngInfoThng/2025-06/page_00001.json",
      "text": "G2B public OpenAPI row. service=backfill_hrcsp_ssstndrd_info. operation=getPublicPrcureThngInfoThng. source_file=raw/getPublicPrcureThngInfoThng/2025-06/page_00001.json. row_index=35. bfSpecRgstNo=R25BD00075560; bidNtceNoList=R25BK00897955,R25BK00916147; ofclNm=김재현; ofclTelNo=02-2228-0225; prdctClsfcNoNm=연구용서버 및 부속품 구매; rlDminsttNm=연세대학교의료원 산학협력단; asignBdgtAmt=62612000; bsnsDivNm=물품; chgDt=2025-06-02 10:04:23; dlvrDaynum=60; opninRgstClseDt=2025-06-07 23:59:00; orderInsttNm=연세대학교의료원 산학협력단; prdctDtlList=[1^4321150102^컴퓨터서버]; rcptDt=2025-06-02 10:04:23; refNo=2024-31-1397/p25-003326; rgstDt=2025-06-02 10:04:20; specDocFileUrl1=https://www.g2b.go.kr/pn/pnz/pnza/UntyAtchFile/downloadFile.do?bfSpecRegNo=R25BD00075560&fileType=BFDTL&fileSeq=1; swBizObjYn=N.",
      "hash": "sha256:776cb87b9e3a9fd7c2b668c3f575224cf81fab0dd1fe46710b54687f329771c5",
      "source_path": "backfill_hrcsp_ssstndrd_info/raw/getPublicPrcureThngInfoThng/2025-06/page_00001.json"
    },
    {
      "source_line": 4706,
      "chunk_id": "chunk:g2b:sentence:8271b410ebd1913cdcd0db80",
      "evidence_id": "evidence:g2b:sentence:row:06a1be4af9438558fcbe66df",
      "document_id": "doc:g2b:source:7b163281f6da85630a69aafe",
      "service": "backfill_hrcsp_ssstndrd_info",
      "operation": "getPublicPrcureThngInfoThng",
      "source_file": "backfill_hrcsp_ssstndrd_info/raw/getPublicPrcureThngInfoThng/2025-06/page_00001.json",
      "text": "G2B public OpenAPI row. service=backfill_hrcsp_ssstndrd_info. operation=getPublicPrcureThngInfoThng. source_file=raw/getPublicPrcureThngInfoThng/2025-06/page_00001.json. row_index=36. bfSpecRgstNo=R25BD00075562; bidNtceNoList=R25BK00891503; ofclNm=박철; ofclTelNo=033-650-3214; prdctClsfcNoNm=삼척 지역특화 임대형 스마트팜 조성사업 온실공사 관급자재 구매; rlDminsttNm=한국농어촌공사 강원지역본부 강릉지사; asignBdgtAmt=560323500; bsnsDivNm=물품; chgDt=2025-06-02 10:05:31; dlvrDaynum=0; dlvrTmlmtDt=2025-10-30 00:00:00; opninRgstClseDt=2025-06-07 23:59:00; orderInsttNm=한국농어촌공사 강원지역본부 강릉지사; prdctDtlList=[1^3015180201^샌드위치패널]; rcptDt=2025-06-02 10:05:31; refNo=한국농어촌공사 강릉지사 공고 제2025-90호; rgstDt=2025-06-02 10:05:29; specDocFileUrl1=https://www.g2b.go.kr/pn/pnz/pnza/UntyAtchFile/downloadFile.do?bfSpecRegNo=R25BD00075562&fileType=BFDTL&fileSeq=1; specDocFileUrl2=https://www.g2b.go.kr/pn/pnz/pnza/UntyAtchFile/downloadFile.do?bfSpecRegNo=R25BD00075562&fileType=BFDTL&fileSeq=2; specDocFileUrl3=https://www.g2b.go.kr/pn/pnz/pnza/UntyAtchFile/downloadFile.do?bfSpecRegNo=R25BD00075562&fileType=BFDTL&fileSeq=3; swBizObjYn=N.",
      "hash": "sha256:b1fa7504627086d52c173039c454cd5297701e999a8af6f915a26bfd545d0a5e",
      "source_path": "backfill_hrcsp_ssstndrd_info/raw/getPublicPrcureThngInfoThng/2025-06/page_00001.json"
    },
    {
      "source_line": 4707,
      "chunk_id": "chunk:g2b:sentence:53eddecbb33965fa11234039",
      "evidence_id": "evidence:g2b:sentence:row:449f3e1a351d9fd9e1716075",
      "document_id": "doc:g2b:source:7b163281f6da85630a69aafe",
      "service": "backfill_hrcsp_ssstndrd_info",
      "operation": "getPublicPrcureThngInfoThng",
      "source_file": "backfill_hrcsp_ssstndrd_info/raw/getPublicPrcureThngInfoThng/2025-06/page_00001.json",
      "text": "G2B public OpenAPI row. service=backfill_hrcsp_ssstndrd_info. operation=getPublicPrcureThngInfoThng. source_file=raw/getPublicPrcureThngInfoThng/2025-06/page_00001.json. row_index=37. bfSpecRgstNo=R25BD00075563; prdctClsfcNoNm=분당관리소 가스히터 구매; rlDminsttNm=한국가스공사; asignBdgtAmt=2728262900; bsnsDivNm=물품; dlvrTmlmtDt=2026-05-31 00:00:00; opninRgstClseDt=2025-06-09 00:00:00; orderInsttNm=한국가스공사; prdctDtlList=[1^^분당관리소 가스히터 구매]; rcptDt=2025-06-02 10:07:01; refNo=A250602002; rgstDt=2025-06-02 10:07:01; swBizObjYn=N.",
      "hash": "sha256:c71d6dfab9abbb54dd1b790182cce42935a599cbaf0bccefcdfe797bcee75813",
      "source_path": "backfill_hrcsp_ssstndrd_info/raw/getPublicPrcureThngInfoThng/2025-06/page_00001.json"
    },
    {
      "source_line": 4708,
      "chunk_id": "chunk:g2b:sentence:37719b62db5bae6f665eaf9d",
      "evidence_id": "evidence:g2b:sentence:row:ce3f0b0370e7cec32254e410",
      "document_id": "doc:g2b:source:7b163281f6da85630a69aafe",
      "service": "backfill_hrcsp_ssstndrd_info",
      "operation": "getPublicPrcureThngInfoThng",
      "source_file": "backfill_hrcsp_ssstndrd_info/raw/getPublicPrcureThngInfoThng/2025-06/page_00001.json",
      "text": "G2B public OpenAPI row. service=backfill_hrcsp_ssstndrd_info. operation=getPublicPrcureThngInfoThng. source_file=raw/getPublicPrcureThngInfoThng/2025-06/page_00001.json. row_index=38. bfSpecRgstNo=R25BD00075564; bidNtceNoList=R25BK00889996; ofclNm=최진; prdctClsfcNoNm=진주교도소 급식용 공산품 3차 구매(규격,가격 동시) 입찰공고; rlDminsttNm=법무부 대구지방교정청 진주교도소; asignBdgtAmt=180000000; bsnsDivNm=물품; chgDt=2025-06-02 10:07:21; dlvrDaynum=0; dlvrTmlmtDt=2025-09-30 00:00:00; opninRgstClseDt=2025-06-07 23:59:00; orderInsttNm=법무부 대구지방교정청 진주교도소; prdctDtlList=[1^5017200101^간장]; rcptDt=2025-06-02 10:07:21; refNo=진주교도소0602; rgstDt=2025-06-02 10:07:18; specDocFileUrl1=https://www.g2b.go.kr/pn/pnz/pnza/UntyAtchFile/downloadFile.do?bfSpecRegNo=R25BD00075564&fileType=BFDTL&fileSeq=1; swBizObjYn=N.",
      "hash": "sha256:8dd9c44bd1603fd6613c4642ed04997a2231d4b9a83e6fa0b4c0b6f07617904c",
      "source_path": "backfill_hrcsp_ssstndrd_info/raw/getPublicPrcureThngInfoThng/2025-06/page_00001.json"
    },
    {
      "source_line": 4709,
      "chunk_id": "chunk:g2b:sentence:5f4a1e474e965c50caf78678",
      "evidence_id": "evidence:g2b:sentence:row:9b7d90bdade3c092fe4599df",
      "document_id": "doc:g2b:source:7b163281f6da85630a69aafe",
      "service": "backfill_hrcsp_ssstndrd_info",
      "operation": "getPublicPrcureThngInfoThng",
      "source_file": "backfill_hrcsp_ssstndrd_info/raw/getPublicPrcureThngInfoThng/2025-06/page_00001.json",
      "text": "G2B public OpenAPI row. service=backfill_hrcsp_ssstndrd_info. operation=getPublicPrcureThngInfoThng. source_file=raw/getPublicPrcureThngInfoThng/2025-06/page_00001.json. row_index=39. bfSpecRgstNo=R25BD00075565; bidNtceNoList=R25BK00891233; ofclNm=강민지; ofclTelNo=054-550-8357; prdctClsfcNoNm=CCTV 통합관제센터 저장분배서버 구매; rlDminsttNm=경상북도 문경시; asignBdgtAmt=87000000; bsnsDivNm=물품; chgDt=2025-06-02 10:07:39; dlvrDaynum=60; opninRgstClseDt=2025-06-07 23:59:00; orderInsttNm=경상북도 문경시; prdctDtlList=[1^4321150102^컴퓨터서버]; rcptDt=2025-06-02 10:07:39; refNo=홍보전산과-6401(2025.05.22.)호; rgstDt=2025-06-02 10:07:37; specDocFileUrl1=https://www.g2b.go.kr/pn/pnz/pnza/UntyAtchFile/downloadFile.do?bfSpecRegNo=R25BD00075565&fileType=BFDTL&fileSeq=1; swBizObjYn=N.",
      "hash": "sha256:03408ae64aac693e6f3f7969e1fe206e35becdcc03d1b9cd32116c3df9e6af24",
      "source_path": "backfill_hrcsp_ssstndrd_info/raw/getPublicPrcureThngInfoThng/2025-06/page_00001.json"
    },
    {
      "source_line": 4710,
      "chunk_id": "chunk:g2b:sentence:035f506e971bb30c49f8b36a",
      "evidence_id": "evidence:g2b:sentence:row:b882886123d61035e97fc9a1",
      "document_id": "doc:g2b:source:7b163281f6da85630a69aafe",
      "service": "backfill_hrcsp_ssstndrd_info",
      "operation": "getPublicPrcureThngInfoThng",
      "source_file": "backfill_hrcsp_ssstndrd_info/raw/getPublicPrcureThngInfoThng/2025-06/page_00001.json",
      "text": "G2B public OpenAPI row. service=backfill_hrcsp_ssstndrd_info. operation=getPublicPrcureThngInfoThng. source_file=raw/getPublicPrcureThngInfoThng/2025-06/page_00001.json. row_index=40. bfSpecRgstNo=R25BD00075568; bidNtceNoList=R25BK00892384; ofclNm=서승우; ofclTelNo=063-219-2383; prdctClsfcNoNm=에티오피아 농기계R&D센터 조성사업 지자재 구매; rlDminsttNm=재단법인 전북테크노파크; asignBdgtAmt=102840000; bsnsDivNm=물품; chgDt=2025-06-02 10:09:54; dlvrDaynum=180; opninRgstClseDt=2025-06-07 23:59:00; orderInsttNm=재단법인 전북테크노파크; prdctDtlList=[1^2110150101^쟁기]; rcptDt=2025-06-02 10:09:54; refNo=사전공개 제2025-06호; rgstDt=2025-06-02 10:09:52; specDocFileUrl1=https://www.g2b.go.kr/pn/pnz/pnza/UntyAtchFile/downloadFile.do?bfSpecRegNo=R25BD00075568&fileType=BFDTL&fileSeq=1; specDocFileUrl2=https://www.g2b.go.kr/pn/pnz/pnza/UntyAtchFile/downloadFile.do?bfSpecRegNo=R25BD00075568&fileType=BFDTL&fileSeq=2; specDocFileUrl3=https://www.g2b.go.kr/pn/pnz/pnza/UntyAtchFile/downloadFile.do?bfSpecRegNo=R25BD00075568&fileType=BFDTL&fileSeq=3; swBizObjYn=N.",
      "hash": "sha256:6b84f2370667bd3b76f26a0a2a332bd38b861d111a1751084926d0a557adde3e",
      "source_path": "backfill_hrcsp_ssstndrd_info/raw/getPublicPrcureThngInfoThng/2025-06/page_00001.json"
    },
    {
      "source_line": 4711,
      "chunk_id": "chunk:g2b:sentence:2a8899f396f65f219fb7e9c8",
      "evidence_id": "evidence:g2b:sentence:row:64d94086a61f6b1b148beac4",
      "document_id": "doc:g2b:source:7b163281f6da85630a69aafe",
      "service": "backfill_hrcsp_ssstndrd_info",
      "operation": "getPublicPrcureThngInfoThng",
      "source_file": "backfill_hrcsp_ssstndrd_info/raw/getPublicPrcureThngInfoThng/2025-06/page_00001.json",
      "text": "G2B public OpenAPI row. service=backfill_hrcsp_ssstndrd_info. operation=getPublicPrcureThngInfoThng. source_file=raw/getPublicPrcureThngInfoThng/2025-06/page_00001.json. row_index=41. bfSpecRgstNo=R25BD00075576; bidNtceNoList=R25BK00891583; ofclNm=박선미; ofclTelNo=053-616-0260; prdctClsfcNoNm=식자재; rlDminsttNm=달성군장애인복지관; asignBdgtAmt=45000000; bsnsDivNm=물품; chgDt=2025-06-02 10:17:56; dlvrDaynum=0; dlvrTmlmtDt=2025-07-01 00:00:00; opninRgstClseDt=2025-06-07 23:59:00; orderInsttNm=달성군장애인복지관; prdctDtlList=[1^5022129701^식사대용식품]; rcptDt=2025-06-02 10:17:56; refNo=달성장복 2025-1406; rgstDt=2025-06-02 10:17:53; specDocFileUrl1=https://www.g2b.go.kr/pn/pnz/pnza/UntyAtchFile/downloadFile.do?bfSpecRegNo=R25BD00075576&fileType=BFDTL&fileSeq=1; swBizObjYn=N.",
      "hash": "sha256:267b37e7a8750f1d4412fc0dd9556c507c4804432ffa6c5e8b0ebbb9072e3f9e",
      "source_path": "backfill_hrcsp_ssstndrd_info/raw/getPublicPrcureThngInfoThng/2025-06/page_00001.json"
    },
    {
      "source_line": 4712,
      "chunk_id": "chunk:g2b:sentence:323619385c1ac4761c5d2090",
      "evidence_id": "evidence:g2b:sentence:row:a41aaf1715e6d7811e8d52b0",
      "document_id": "doc:g2b:source:7b163281f6da85630a69aafe",
      "service": "backfill_hrcsp_ssstndrd_info",
      "operation": "getPublicPrcureThngInfoThng",
      "source_file": "backfill_hrcsp_ssstndrd_info/raw/getPublicPrcureThngInfoThng/2025-06/page_00001.json",
      "text": "G2B public OpenAPI row. service=backfill_hrcsp_ssstndrd_info. operation=getPublicPrcureThngInfoThng. source_file=raw/getPublicPrcureThngInfoThng/2025-06/page_00001.json. row_index=42. bfSpecRgstNo=R25BD00075580; bidNtceNoList=R25BK00893705; ofclNm=이재중; ofclTelNo=041-851-3213; prdctClsfcNoNm=공주교도소 장류작업장 수입산 건고추 구매 입찰 공고 ; rlDminsttNm=법무부 대전지방교정청 공주교도소; asignBdgtAmt=208200000; bsnsDivNm=물품; chgDt=2025-06-02 10:22:38; dlvrDaynum=180; opninRgstClseDt=2025-06-07 23:59:00; orderInsttNm=법무부 대전지방교정청 공주교도소; prdctDtlList=[1^5017155301^고춧가루및실고추]; rcptDt=2025-06-02 10:22:38; refNo=공주교도소 공고 제2025-00호; rgstDt=2025-06-02 10:22:35; specDocFileUrl1=https://www.g2b.go.kr/pn/pnz/pnza/UntyAtchFile/downloadFile.do?bfSpecRegNo=R25BD00075580&fileType=BFDTL&fileSeq=1; specDocFileUrl2=https://www.g2b.go.kr/pn/pnz/pnza/UntyAtchFile/downloadFile.do?bfSpecRegNo=R25BD00075580&fileType=BFDTL&fileSeq=2; specDocFileUrl3=https://www.g2b.go.kr/pn/pnz/pnza/UntyAtchFile/downloadFile.do?bfSpecRegNo=R25BD00075580&fileType=BFDTL&fileSeq=3; specDocFileUrl4=https://www.g2b.go.kr/pn/pnz/pnza/UntyAtchFile/downloadFile.do?bfSpecRegNo=R25BD00075580&fileType=BFDTL&fileSeq=4; swBizObjYn=N.",
      "hash": "sha256:bb0540261d6acd4aa1ea270b58e9912b799c745bfd361f409889b5a1085929b9",
      "source_path": "backfill_hrcsp_ssstndrd_info/raw/getPublicPrcureThngInfoThng/2025-06/page_00001.json"
    },
    {
      "source_line": 4713,
      "chunk_id": "chunk:g2b:sentence:690eb66c51fd9c69583945a7",
      "evidence_id": "evidence:g2b:sentence:row:984fbe2fc2e8d0fa2de12873",
      "document_id": "doc:g2b:source:7b163281f6da85630a69aafe",
      "service": "backfill_hrcsp_ssstndrd_info",
      "operation": "getPublicPrcureThngInfoThng",
      "source_file": "backfill_hrcsp_ssstndrd_info/raw/getPublicPrcureThngInfoThng/2025-06/page_00001.json",
      "text": "G2B public OpenAPI row. service=backfill_hrcsp_ssstndrd_info. operation=getPublicPrcureThngInfoThng. source_file=raw/getPublicPrcureThngInfoThng/2025-06/page_00001.json. row_index=43. bfSpecRgstNo=R25BD00075581; bidNtceNoList=R25BK00904120; ofclNm=김지훈; ofclTelNo=070-4056-8923; prdctClsfcNoNm=(글로컬대학) 전북대학교 이차전지 Dry Room(청정룸) 구매 설치; rlDminsttNm=전북대학교; asignBdgtAmt=511594630; bsnsDivNm=물품; chgDt=2025-06-02 10:23:14; dlvrDaynum=150; opninRgstClseDt=2025-06-09 23:59:00; orderInsttNm=조달청 전북지방조달청; prdctDtlList=[1^3020170401^청정실]; rcptDt=2025-06-02 10:23:14; refNo=시설과-5534; rgstDt=2025-06-02 10:23:12; specDocFileUrl1=https://www.g2b.go.kr/pn/pnz/pnza/UntyAtchFile/downloadFile.do?bfSpecRegNo=R25BD00075581&fileType=BFDTL&fileSeq=1; specDocFileUrl2=https://www.g2b.go.kr/pn/pnz/pnza/UntyAtchFile/downloadFile.do?bfSpecRegNo=R25BD00075581&fileType=BFDTL&fileSeq=2; specDocFileUrl3=https://www.g2b.go.kr/pn/pnz/pnza/UntyAtchFile/downloadFile.do?bfSpecRegNo=R25BD00075581&fileType=BFDTL&fileSeq=3; swBizObjYn=N.",
      "hash": "sha256:4930c30caa91ef0d0b1d2cde29d3c5a4c5f42c99713dd92fc67ae18f8354b475",
      "source_path": "backfill_hrcsp_ssstndrd_info/raw/getPublicPrcureThngInfoThng/2025-06/page_00001.json"
    },
    {
      "source_line": 4714,
      "chunk_id": "chunk:g2b:sentence:e10beda1be4178d16c2b6d1b",
      "evidence_id": "evidence:g2b:sentence:row:051a6e00fe37ba361e19ea6a",
      "document_id": "doc:g2b:source:7b163281f6da85630a69aafe",
      "service": "backfill_hrcsp_ssstndrd_info",
      "operation": "getPublicPrcureThngInfoThng",
      "source_file": "backfill_hrcsp_ssstndrd_info/raw/getPublicPrcureThngInfoThng/2025-06/page_00001.json",
      "text": "G2B public OpenAPI row. service=backfill_hrcsp_ssstndrd_info. operation=getPublicPrcureThngInfoThng. source_file=raw/getPublicPrcureThngInfoThng/2025-06/page_00001.json. row_index=44. bfSpecRgstNo=R25BD00075582; bidNtceNoList=R25BK00980807; ofclNm=추지연; ofclTelNo=053-605-8263; prdctClsfcNoNm=생물반응조 교반기 구매·설치; rlDminsttNm=대구공공시설관리공단 북부사업처; asignBdgtAmt=99880000; bsnsDivNm=물품; chgDt=2025-06-02 10:23:19; dlvrDaynum=120; opninRgstClseDt=2025-06-07 23:59:00; orderInsttNm=대구공공시설관리공단 북부사업처; prdctDtlList=[1^4710151201^교반기]; rcptDt=2025-06-02 10:23:19; refNo=발주계획 참조; rgstDt=2025-06-02 10:23:17; specDocFileUrl1=https://www.g2b.go.kr/pn/pnz/pnza/UntyAtchFile/downloadFile.do?bfSpecRegNo=R25BD00075582&fileType=BFDTL&fileSeq=1; swBizObjYn=N.",
      "hash": "sha256:9070bff5eba5894ab78786a1633ef1542f32165a7ccfeaf7bcefbf53e01a6703",
      "source_path": "backfill_hrcsp_ssstndrd_info/raw/getPublicPrcureThngInfoThng/2025-06/page_00001.json"
    },
    {
      "source_line": 4715,
      "chunk_id": "chunk:g2b:sentence:07826c247e6a87a3426fe69f",
      "evidence_id": "evidence:g2b:sentence:row:91072d60eddc5e750c84be5b",
      "document_id": "doc:g2b:source:7b163281f6da85630a69aafe",
      "service": "backfill_hrcsp_ssstndrd_info",
      "operation": "getPublicPrcureThngInfoThng",
      "source_file": "backfill_hrcsp_ssstndrd_info/raw/getPublicPrcureThngInfoThng/2025-06/page_00001.json",
      "text": "G2B public OpenAPI row. service=backfill_hrcsp_ssstndrd_info. operation=getPublicPrcureThngInfoThng. source_file=raw/getPublicPrcureThngInfoThng/2025-06/page_00001.json. row_index=45. bfSpecRgstNo=R25BD00075585; ofclNm=김재훈; ofclTelNo=033-259-6212; prdctClsfcNoNm=인제종합운동장 조성사업 관급자재(조명타워) 구매; rlDminsttNm=강원개발공사; asignBdgtAmt=1770875000; bsnsDivNm=물품; chgDt=2025-06-02 10:25:09; dlvrDaynum=520; opninRgstClseDt=2025-06-05 23:59:00; orderInsttNm=강원개발공사; prdctDtlList=[1^3911200101^조명타워],[2^3911153701^스포츠조명기구]; rcptDt=2025-06-02 10:25:09; refNo=재무계약부-2655; rgstDt=2025-06-02 10:25:03; specDocFileUrl1=https://www.g2b.go.kr/pn/pnz/pnza/UntyAtchFile/downloadFile.do?bfSpecRegNo=R25BD00075585&fileType=BFDTL&fileSeq=1; specDocFileUrl2=https://www.g2b.go.kr/pn/pnz/pnza/UntyAtchFile/downloadFile.do?bfSpecRegNo=R25BD00075585&fileType=BFDTL&fileSeq=2; specDocFileUrl3=https://www.g2b.go.kr/pn/pnz/pnza/UntyAtchFile/downloadFile.do?bfSpecRegNo=R25BD00075585&fileType=BFDTL&fileSeq=3; specDocFileUrl4=https://www.g2b.go.kr/pn/pnz/pnza/UntyAtchFile/downloadFile.do?bfSpecRegNo=R25BD00075585&fileType=BFDTL&fileSeq=4; specDocFileUrl5=https://www.g2b.go.kr/pn/pnz/pnza/UntyAtchFile/downloadFile.do?bfSpecRegNo=R25BD00075585&fileType=BFDTL&fileSeq=5; swBizObjYn=N.",
      "hash": "sha256:483b06f2839b9fa675c78bf3dfc31262855fb048221abe5881a9a4378aac6d14",
      "source_path": "backfill_hrcsp_ssstndrd_info/raw/getPublicPrcureThngInfoThng/2025-06/page_00001.json"
    },
    {
      "source_line": 4716,
      "chunk_id": "chunk:g2b:sentence:a0b0dc28e6b5b178c2ab883f",
      "evidence_id": "evidence:g2b:sentence:row:332d363a87342dcc42af1afd",
      "document_id": "doc:g2b:source:7b163281f6da85630a69aafe",
      "service": "backfill_hrcsp_ssstndrd_info",
      "operation": "getPublicPrcureThngInfoThng",
      "source_file": "backfill_hrcsp_ssstndrd_info/raw/getPublicPrcureThngInfoThng/2025-06/page_00001.json",
      "text": "G2B public OpenAPI row. service=backfill_hrcsp_ssstndrd_info. operation=getPublicPrcureThngInfoThng. source_file=raw/getPublicPrcureThngInfoThng/2025-06/page_00001.json. row_index=46. bfSpecRgstNo=R25BD00075586; bidNtceNoList=R25BK00880911; ofclNm=김재희; ofclTelNo=061-531-3822; prdctClsfcNoNm=[입찰대행]2025년 청년4-H회원 우수과제 창업농 육성 사업(농업용 드론구입); rlDminsttNm=전라남도 해남군 농업기술센터; asignBdgtAmt=40000000; bsnsDivNm=물품; chgDt=2025-06-02 10:26:05; dlvrDaynum=10; opninRgstClseDt=2025-06-07 23:59:00; orderInsttNm=전라남도 해남군 농업기술센터; prdctDtlList=[1^2513189901^드론]; rcptDt=2025-06-02 10:26:05; refNo=해남군농업기술센터 공고 제2025-30호; rgstDt=2025-06-02 10:26:02; specDocFileUrl1=https://www.g2b.go.kr/pn/pnz/pnza/UntyAtchFile/downloadFile.do?bfSpecRegNo=R25BD00075586&fileType=BFDTL&fileSeq=1; swBizObjYn=N.",
      "hash": "sha256:c8242b78d131c61caf860063c07be9330df84d508b5548f229a502bc70b9a72c",
      "source_path": "backfill_hrcsp_ssstndrd_info/raw/getPublicPrcureThngInfoThng/2025-06/page_00001.json"
    },
    {
      "source_line": 4717,
      "chunk_id": "chunk:g2b:sentence:1b05e91ab5030c7f40d8e4d5",
      "evidence_id": "evidence:g2b:sentence:row:f0cc1f05e8779e1a69b31315",
      "document_id": "doc:g2b:source:7b163281f6da85630a69aafe",
      "service": "backfill_hrcsp_ssstndrd_info",
      "operation": "getPublicPrcureThngInfoThng",
      "source_file": "backfill_hrcsp_ssstndrd_info/raw/getPublicPrcureThngInfoThng/2025-06/page_00001.json",
      "text": "G2B public OpenAPI row. service=backfill_hrcsp_ssstndrd_info. operation=getPublicPrcureThngInfoThng. source_file=raw/getPublicPrcureThngInfoThng/2025-06/page_00001.json. row_index=47. bfSpecRgstNo=R25BD00075588; bidNtceNoList=R25BK00897111; ofclNm=안라희; ofclTelNo=070-4056-6307; prdctClsfcNoNm=25년 군용 안면마스크 제조(육군, 공군); rlDminsttNm=육군군수사령부; asignBdgtAmt=183218935; bsnsDivNm=물품; chgDt=2025-06-02 10:30:06; dlvrDaynum=0; dlvrTmlmtDt=2025-05-30 00:00:00; opninRgstClseDt=2025-06-07 23:59:00; orderInsttNm=조달청; prdctDtlList=[1^4618171001^두건],[2^4618171001^두건],[3^4618171001^두건],[4^4618171001^두건]; rcptDt=2025-06-02 10:30:06; refNo=.; rgstDt=2025-06-02 10:30:02; specDocFileUrl1=https://www.g2b.go.kr/pn/pnz/pnza/UntyAtchFile/downloadFile.do?bfSpecRegNo=R25BD00075588&fileType=BFDTL&fileSeq=1; specDocFileUrl2=https://www.g2b.go.kr/pn/pnz/pnza/UntyAtchFile/downloadFile.do?bfSpecRegNo=R25BD00075588&fileType=BFDTL&fileSeq=2; swBizObjYn=N.",
      "hash": "sha256:526a7b27d0e2b7c9064909bbfaeab66db01a7315113341c126020f9c6bfa6c77",
      "source_path": "backfill_hrcsp_ssstndrd_info/raw/getPublicPrcureThngInfoThng/2025-06/page_00001.json"
    },
    {
      "source_line": 4718,
      "chunk_id": "chunk:g2b:sentence:30ec96108fbe59a3d780ba2e",
      "evidence_id": "evidence:g2b:sentence:row:10d65b8df509918979061451",
      "document_id": "doc:g2b:source:7b163281f6da85630a69aafe",
      "service": "backfill_hrcsp_ssstndrd_info",
      "operation": "getPublicPrcureThngInfoThng",
      "source_file": "backfill_hrcsp_ssstndrd_info/raw/getPublicPrcureThngInfoThng/2025-06/page_00001.json",
      "text": "G2B public OpenAPI row. service=backfill_hrcsp_ssstndrd_info. operation=getPublicPrcureThngInfoThng. source_file=raw/getPublicPrcureThngInfoThng/2025-06/page_00001.json. row_index=48. bfSpecRgstNo=R25BD00075590; bidNtceNoList=R25BK00885660; ofclNm=홍석원; ofclTelNo=02-2610-1993; prdctClsfcNoNm=혁신지원사업 바이오융합공학과 실험실습기자재(물성데이터획득장치) 구입; rlDminsttNm=동양미래대학교 산학협력단; asignBdgtAmt=42900000; bsnsDivNm=물품; chgDt=2025-06-02 10:30:48; dlvrDaynum=60; opninRgstClseDt=2025-06-07 23:59:00; orderInsttNm=동양미래대학교 산학협력단; prdctDtlList=[1^8610169601^기타교육서비스]; rcptDt=2025-06-02 10:30:48; refNo=산단 제2025-00호; rgstDt=2025-06-02 10:30:46; specDocFileUrl1=https://www.g2b.go.kr/pn/pnz/pnza/UntyAtchFile/downloadFile.do?bfSpecRegNo=R25BD00075590&fileType=BFDTL&fileSeq=1; specDocFileUrl2=https://www.g2b.go.kr/pn/pnz/pnza/UntyAtchFile/downloadFile.do?bfSpecRegNo=R25BD00075590&fileType=BFDTL&fileSeq=2; swBizObjYn=N.",
      "hash": "sha256:8b1e0236656cb1695119be399f58869b55ebcafa7c9f6a075e74a59fa7e42eaa",
      "source_path": "backfill_hrcsp_ssstndrd_info/raw/getPublicPrcureThngInfoThng/2025-06/page_00001.json"
    },
    {
      "source_line": 4719,
      "chunk_id": "chunk:g2b:sentence:603f82548d3ff4381d83cb28",
      "evidence_id": "evidence:g2b:sentence:row:b4c4b44e59d5db75877b2c97",
      "document_id": "doc:g2b:source:7b163281f6da85630a69aafe",
      "service": "backfill_hrcsp_ssstndrd_info",
      "operation": "getPublicPrcureThngInfoThng",
      "source_file": "backfill_hrcsp_ssstndrd_info/raw/getPublicPrcureThngInfoThng/2025-06/page_00001.json",
      "text": "G2B public OpenAPI row. service=backfill_hrcsp_ssstndrd_info. operation=getPublicPrcureThngInfoThng. source_file=raw/getPublicPrcureThngInfoThng/2025-06/page_00001.json. row_index=49. bfSpecRgstNo=R25BD00075592; bidNtceNoList=R25BK00908002,R25BK00926275,R25BK00951305; ofclNm=이상현; prdctClsfcNoNm=AEBS 평가용 자동차 더미(EVT) 구매; rlDminsttNm=한국교통안전공단 자동차안전연구원; asignBdgtAmt=50000000; bsnsDivNm=물품; chgDt=2025-06-02 10:41:00; dlvrDaynum=90; opninRgstClseDt=2025-06-07 23:59:00; orderInsttNm=한국교통안전공단 자동차안전연구원; prdctDtlList=[1^2522100801^전동차용제어차대차(저항제어)]; rcptDt=2025-06-02 10:41:00; refNo=규격 제 2025-40호; rgstDt=2025-06-02 10:34:50; specDocFileUrl1=https://www.g2b.go.kr/pn/pnz/pnza/UntyAtchFile/downloadFile.do?bfSpecRegNo=R25BD00075592&fileType=BFDTL&fileSeq=1; specDocFileUrl2=https://www.g2b.go.kr/pn/pnz/pnza/UntyAtchFile/downloadFile.do?bfSpecRegNo=R25BD00075592&fileType=BFDTL&fileSeq=2; specDocFileUrl3=https://www.g2b.go.kr/pn/pnz/pnza/UntyAtchFile/downloadFile.do?bfSpecRegNo=R25BD00075592&fileType=BFDTL&fileSeq=3; swBizObjYn=N.",
      "hash": "sha256:db1ae5d2f45e9527d35e9a874f2a0d1d4676080a1bd43c34d1179a0eecd1ed81",
      "source_path": "backfill_hrcsp_ssstndrd_info/raw/getPublicPrcureThngInfoThng/2025-06/page_00001.json"
    },
    {
      "source_line": 4720,
      "chunk_id": "chunk:g2b:sentence:46cfa2074307623bc6607bd9",
      "evidence_id": "evidence:g2b:sentence:row:f8fcd7cafdea97a3ada89684",
      "document_id": "doc:g2b:source:7b163281f6da85630a69aafe",
      "service": "backfill_hrcsp_ssstndrd_info",
      "operation": "getPublicPrcureThngInfoThng",
      "source_file": "backfill_hrcsp_ssstndrd_info/raw/getPublicPrcureThngInfoThng/2025-06/page_00001.json",
      "text": "G2B public OpenAPI row. service=backfill_hrcsp_ssstndrd_info. operation=getPublicPrcureThngInfoThng. source_file=raw/getPublicPrcureThngInfoThng/2025-06/page_00001.json. row_index=50. bfSpecRgstNo=R25BD00075594; bidNtceNoList=R25BK00938791,R25BK00915689; ofclNm=이지은; ofclTelNo=070-4056-8972; prdctClsfcNoNm=(조달위탁)충남서부권 신설(정) 비상발전기 제조구매; rlDminsttNm=한국수자원공사 금강유역본부 금강경영처; asignBdgtAmt=470976700; bsnsDivNm=물품; chgDt=2025-06-02 10:35:42; dlvrDaynum=300; opninRgstClseDt=2025-06-07 23:59:00; orderInsttNm=조달청 전북지방조달청; prdctDtlList=[1^2611160101^디젤발전기]; rcptDt=2025-06-02 10:35:42; refNo=C1202520285; rgstDt=2025-06-02 10:35:40; specDocFileUrl1=https://www.g2b.go.kr/pn/pnz/pnza/UntyAtchFile/downloadFile.do?bfSpecRegNo=R25BD00075594&fileType=BFDTL&fileSeq=1; specDocFileUrl2=https://www.g2b.go.kr/pn/pnz/pnza/UntyAtchFile/downloadFile.do?bfSpecRegNo=R25BD00075594&fileType=BFDTL&fileSeq=2; specDocFileUrl3=https://www.g2b.go.kr/pn/pnz/pnza/UntyAtchFile/downloadFile.do?bfSpecRegNo=R25BD00075594&fileType=BFDTL&fileSeq=3; swBizObjYn=N.",
      "hash": "sha256:2fe88aa9d5e1cf4b51d7bfce7ff64a440bb696eebf1c9b0865da28ab48eedc56",
      "source_path": "backfill_hrcsp_ssstndrd_info/raw/getPublicPrcureThngInfoThng/2025-06/page_00001.json"
    },
    {
      "source_line": 4721,
      "chunk_id": "chunk:g2b:sentence:4807611093fc8eac711fded7",
      "evidence_id": "evidence:g2b:sentence:row:98b6a6c01f711671cbdaccd8",
      "document_id": "doc:g2b:source:7b163281f6da85630a69aafe",
      "service": "backfill_hrcsp_ssstndrd_info",
      "operation": "getPublicPrcureThngInfoThng",
      "source_file": "backfill_hrcsp_ssstndrd_info/raw/getPublicPrcureThngInfoThng/2025-06/page_00001.json",
      "text": "G2B public OpenAPI row. service=backfill_hrcsp_ssstndrd_info. operation=getPublicPrcureThngInfoThng. source_file=raw/getPublicPrcureThngInfoThng/2025-06/page_00001.json. row_index=51. bfSpecRgstNo=R25BD00075598; prdctClsfcNoNm=(256169-C) 트레일러형 작업등 구매; rlDminsttNm=국방부 국군재정관리단; asignBdgtAmt=429000000; bsnsDivNm=물품; dlvrDaynum=0; opninRgstClseDt=2025-06-07 00:00:00; orderInsttNm=국방부 국군재정관리단; prdctDtlList=[1^^(256169-C) 트레일러형 작업등 구매]; rcptDt=2025-06-02 10:40:01; refNo=PS2025UMM22359; rgstDt=2025-06-02 10:40:01; swBizObjYn=N.",
      "hash": "sha256:aa0f6c4ec1f49ff805d15cdf5665752110f82c8c45f28ed4cfc1e2c8fc67f31c",
      "source_path": "backfill_hrcsp_ssstndrd_info/raw/getPublicPrcureThngInfoThng/2025-06/page_00001.json"
    },
    {
      "source_line": 4722,
      "chunk_id": "chunk:g2b:sentence:323683b35da9d16f742a0368",
      "evidence_id": "evidence:g2b:sentence:row:7a2cac15214e17d1f8157f91",
      "document_id": "doc:g2b:source:7b163281f6da85630a69aafe",
      "service": "backfill_hrcsp_ssstndrd_info",
      "operation": "getPublicPrcureThngInfoThng",
      "source_file": "backfill_hrcsp_ssstndrd_info/raw/getPublicPrcureThngInfoThng/2025-06/page_00001.json",
      "text": "G2B public OpenAPI row. service=backfill_hrcsp_ssstndrd_info. operation=getPublicPrcureThngInfoThng. source_file=raw/getPublicPrcureThngInfoThng/2025-06/page_00001.json. row_index=52. bfSpecRgstNo=R25BD00075601; bidNtceNoList=R25BK00948338; ofclNm=안라희; ofclTelNo=070-4056-6307; prdctClsfcNoNm=25년 육군 난연 안면마스크 제조; rlDminsttNm=육군군수사령부; asignBdgtAmt=164618530; bsnsDivNm=물품; chgDt=2025-06-02 10:44:11; dlvrDaynum=0; dlvrTmlmtDt=2025-11-28 00:00:00; opninRgstClseDt=2025-06-07 23:59:00; orderInsttNm=조달청; prdctDtlList=[1^4618171001^두건]; rcptDt=2025-06-02 10:44:11; refNo=.; rgstDt=2025-06-02 10:44:10; specDocFileUrl1=https://www.g2b.go.kr/pn/pnz/pnza/UntyAtchFile/downloadFile.do?bfSpecRegNo=R25BD00075601&fileType=BFDTL&fileSeq=1; specDocFileUrl2=https://www.g2b.go.kr/pn/pnz/pnza/UntyAtchFile/downloadFile.do?bfSpecRegNo=R25BD00075601&fileType=BFDTL&fileSeq=2; specDocFileUrl3=https://www.g2b.go.kr/pn/pnz/pnza/UntyAtchFile/downloadFile.do?bfSpecRegNo=R25BD00075601&fileType=BFDTL&fileSeq=3; swBizObjYn=N.",
      "hash": "sha256:0aa85d6e684d2edb8f35b97072a6203bbae7a0f3525f0dbbd5ba19bf9fa2e463",
      "source_path": "backfill_hrcsp_ssstndrd_info/raw/getPublicPrcureThngInfoThng/2025-06/page_00001.json"
    },
    {
      "source_line": 4723,
      "chunk_id": "chunk:g2b:sentence:e895f97387d0804709a36769",
      "evidence_id": "evidence:g2b:sentence:row:aa7a6952811264841fa13b34",
      "document_id": "doc:g2b:source:7b163281f6da85630a69aafe",
      "service": "backfill_hrcsp_ssstndrd_info",
      "operation": "getPublicPrcureThngInfoThng",
      "source_file": "backfill_hrcsp_ssstndrd_info/raw/getPublicPrcureThngInfoThng/2025-06/page_00001.json",
      "text": "G2B public OpenAPI row. service=backfill_hrcsp_ssstndrd_info. operation=getPublicPrcureThngInfoThng. source_file=raw/getPublicPrcureThngInfoThng/2025-06/page_00001.json. row_index=53. bfSpecRgstNo=R25BD00075604; bidNtceNoList=R25BK00890331; ofclNm=정지현; prdctClsfcNoNm=진해구청 그린빗물인프라 조성공사-셀형토목용보강재; rlDminsttNm=경상남도 창원시; asignBdgtAmt=89712480; bsnsDivNm=물품; chgDt=2025-06-02 10:46:16; dlvrDaynum=0; dlvrTmlmtDt=2025-08-30 00:00:00; opninRgstClseDt=2025-06-07 23:59:00; orderInsttNm=경상남도 창원시; prdctDtlList=[1^3012178402^셀형토목용보강재]; rcptDt=2025-06-02 10:46:16; refNo=환경정책과-9849; rgstDt=2025-06-02 10:46:13; specDocFileUrl1=https://www.g2b.go.kr/pn/pnz/pnza/UntyAtchFile/downloadFile.do?bfSpecRegNo=R25BD00075604&fileType=BFDTL&fileSeq=1; specDocFileUrl2=https://www.g2b.go.kr/pn/pnz/pnza/UntyAtchFile/downloadFile.do?bfSpecRegNo=R25BD00075604&fileType=BFDTL&fileSeq=2; swBizObjYn=N.",
      "hash": "sha256:7b6630cf59441232ff517ea563c0a0d349025531b1914ea864a01505ebc880d1",
      "source_path": "backfill_hrcsp_ssstndrd_info/raw/getPublicPrcureThngInfoThng/2025-06/page_00001.json"
    },
    {
      "source_line": 4724,
      "chunk_id": "chunk:g2b:sentence:45ffbaf23a92a09776d64323",
      "evidence_id": "evidence:g2b:sentence:row:470f2586e4970df219183a97",
      "document_id": "doc:g2b:source:7b163281f6da85630a69aafe",
      "service": "backfill_hrcsp_ssstndrd_info",
      "operation": "getPublicPrcureThngInfoThng",
      "source_file": "backfill_hrcsp_ssstndrd_info/raw/getPublicPrcureThngInfoThng/2025-06/page_00001.json",
      "text": "G2B public OpenAPI row. service=backfill_hrcsp_ssstndrd_info. operation=getPublicPrcureThngInfoThng. source_file=raw/getPublicPrcureThngInfoThng/2025-06/page_00001.json. row_index=54. bfSpecRgstNo=R25BD00075605; bidNtceNoList=R25BK00904216; ofclNm=김혜주; ofclTelNo=070-4056-7773; prdctClsfcNoNm=부천역곡 공공주택지구 조성공사 순환골재; rlDminsttNm=한국토지주택공사 인천지역본부; asignBdgtAmt=278816850; bsnsDivNm=물품; chgDt=2025-06-02 10:53:00; dlvrDaynum=0; dlvrTmlmtDt=2027-12-04 00:00:00; opninRgstClseDt=2025-06-09 23:59:00; orderInsttNm=조달청 인천지방조달청; prdctDtlList=[1^3010990401^순환골재]; rcptDt=2025-06-02 10:53:00; refNo=인천계양부천단지조성3팀-1590호 20250522; rgstDt=2025-06-02 10:46:49; specDocFileUrl1=https://www.g2b.go.kr/pn/pnz/pnza/UntyAtchFile/downloadFile.do?bfSpecRegNo=R25BD00075605&fileType=BFDTL&fileSeq=1; swBizObjYn=N.",
      "hash": "sha256:4d361e627e7ae39c7ce3e3f36249d66f0820bd8d861a5430c49fd5663703fb78",
      "source_path": "backfill_hrcsp_ssstndrd_info/raw/getPublicPrcureThngInfoThng/2025-06/page_00001.json"
    },
    {
      "source_line": 4725,
      "chunk_id": "chunk:g2b:sentence:c5159f1a490e7632143d6cfe",
      "evidence_id": "evidence:g2b:sentence:row:e32c5d5a2fd4f7a12eaaca7f",
      "document_id": "doc:g2b:source:7b163281f6da85630a69aafe",
      "service": "backfill_hrcsp_ssstndrd_info",
      "operation": "getPublicPrcureThngInfoThng",
      "source_file": "backfill_hrcsp_ssstndrd_info/raw/getPublicPrcureThngInfoThng/2025-06/page_00001.json",
      "text": "G2B public OpenAPI row. service=backfill_hrcsp_ssstndrd_info. operation=getPublicPrcureThngInfoThng. source_file=raw/getPublicPrcureThngInfoThng/2025-06/page_00001.json. row_index=55. bfSpecRgstNo=R25BD00075608; bidNtceNoList=R25BK00890314; ofclNm=강신오; prdctClsfcNoNm=축산분야 ICT육복합 확산사업 은창목장 발정탐지기 물품 구입; rlDminsttNm=은창목장; asignBdgtAmt=39000000; bsnsDivNm=물품; chgDt=2025-06-02 10:48:40; dlvrDaynum=90; opninRgstClseDt=2025-06-07 23:59:00; orderInsttNm=은창목장; prdctDtlList=[1^4220170202^동물 임신진단기]; rcptDt=2025-06-02 10:48:40; refNo=은창목장 2025-06; rgstDt=2025-06-02 10:48:37; specDocFileUrl1=https://www.g2b.go.kr/pn/pnz/pnza/UntyAtchFile/downloadFile.do?bfSpecRegNo=R25BD00075608&fileType=BFDTL&fileSeq=1; swBizObjYn=N.",
      "hash": "sha256:c40fe14800c9ba959a3a0ff1a96918e905dd9d7b20aaea3ced0c73dc01fb0d18",
      "source_path": "backfill_hrcsp_ssstndrd_info/raw/getPublicPrcureThngInfoThng/2025-06/page_00001.json"
    },
    {
      "source_line": 4726,
      "chunk_id": "chunk:g2b:sentence:2434f9d5622f60bec5dd5718",
      "evidence_id": "evidence:g2b:sentence:row:cb05d732e4df9b842095f94f",
      "document_id": "doc:g2b:source:7b163281f6da85630a69aafe",
      "service": "backfill_hrcsp_ssstndrd_info",
      "operation": "getPublicPrcureThngInfoThng",
      "source_file": "backfill_hrcsp_ssstndrd_info/raw/getPublicPrcureThngInfoThng/2025-06/page_00001.json",
      "text": "G2B public OpenAPI row. service=backfill_hrcsp_ssstndrd_info. operation=getPublicPrcureThngInfoThng. source_file=raw/getPublicPrcureThngInfoThng/2025-06/page_00001.json. row_index=56. bfSpecRgstNo=R25BD00075614; bidNtceNoList=R25BK00890604; ofclNm=조강원; ofclTelNo=031-728-7092; prdctClsfcNoNm=2025년 시각장애인 훈련생 정보화기기(점자정보단말기) 구매; rlDminsttNm=한국장애인고용공단; asignBdgtAmt=126000000; bsnsDivNm=물품; chgDt=2025-06-02 10:55:31; dlvrDaynum=15; opninRgstClseDt=2025-06-05 23:59:00; orderInsttNm=한국장애인고용공단; prdctDtlList=[1^4221170201^시각장애인용컴퓨터]; rcptDt=2025-06-02 10:55:31; refNo=운영지원부-2889; rgstDt=2025-06-02 10:54:01; specDocFileUrl1=https://www.g2b.go.kr/pn/pnz/pnza/UntyAtchFile/downloadFile.do?bfSpecRegNo=R25BD00075614&fileType=BFDTL&fileSeq=1; swBizObjYn=N.",
      "hash": "sha256:26e6f01afc1e98cebb1b756f3e6275f07f544dc8fad3a380dd3b4023c9639370",
      "source_path": "backfill_hrcsp_ssstndrd_info/raw/getPublicPrcureThngInfoThng/2025-06/page_00001.json"
    },
    {
      "source_line": 4727,
      "chunk_id": "chunk:g2b:sentence:cee37f642d93debb536b91f1",
      "evidence_id": "evidence:g2b:sentence:row:6ab449c819d9600ac86622fe",
      "document_id": "doc:g2b:source:7b163281f6da85630a69aafe",
      "service": "backfill_hrcsp_ssstndrd_info",
      "operation": "getPublicPrcureThngInfoThng",
      "source_file": "backfill_hrcsp_ssstndrd_info/raw/getPublicPrcureThngInfoThng/2025-06/page_00001.json",
      "text": "G2B public OpenAPI row. service=backfill_hrcsp_ssstndrd_info. operation=getPublicPrcureThngInfoThng. source_file=raw/getPublicPrcureThngInfoThng/2025-06/page_00001.json. row_index=57. bfSpecRgstNo=R25BD00075618; bidNtceNoList=R25BK00898126; ofclNm=조선영; ofclTelNo=070-4056-8943; prdctClsfcNoNm=동진지사 신호지구 배수개선사업 문비문틀, 수문권양기 제조구매설치; rlDminsttNm=한국농어촌공사 전북지역본부; asignBdgtAmt=666502000; bsnsDivNm=물품; chgDt=2025-06-02 11:00:29; dlvrDaynum=60; opninRgstClseDt=2025-06-07 23:59:00; orderInsttNm=조달청 전북지방조달청; prdctDtlList=[1^4014178401^수문문비]; rcptDt=2025-06-02 11:00:29; refNo=전북농지관리-3662; rgstDt=2025-06-02 11:00:27; specDocFileUrl1=https://www.g2b.go.kr/pn/pnz/pnza/UntyAtchFile/downloadFile.do?bfSpecRegNo=R25BD00075618&fileType=BFDTL&fileSeq=1; swBizObjYn=N.",
      "hash": "sha256:f648c1f6561f76a9486082adac1323ef341cffba83ce11eb9f495fb54f97afb2",
      "source_path": "backfill_hrcsp_ssstndrd_info/raw/getPublicPrcureThngInfoThng/2025-06/page_00001.json"
    },
    {
      "source_line": 4728,
      "chunk_id": "chunk:g2b:sentence:7e1ed7ad7d2c9b594c623138",
      "evidence_id": "evidence:g2b:sentence:row:12344cdad00c603473f05346",
      "document_id": "doc:g2b:source:7b163281f6da85630a69aafe",
      "service": "backfill_hrcsp_ssstndrd_info",
      "operation": "getPublicPrcureThngInfoThng",
      "source_file": "backfill_hrcsp_ssstndrd_info/raw/getPublicPrcureThngInfoThng/2025-06/page_00001.json",
      "text": "G2B public OpenAPI row. service=backfill_hrcsp_ssstndrd_info. operation=getPublicPrcureThngInfoThng. source_file=raw/getPublicPrcureThngInfoThng/2025-06/page_00001.json. row_index=58. bfSpecRgstNo=R25BD00075622; bidNtceNoList=R25BK00899479; ofclNm=이옥경; ofclTelNo=031-729-2742; prdctClsfcNoNm=성남하이테크밸리 청년친화형 아름다운거리 조성사업(미디어시설물 제작 설치); rlDminsttNm=경기도 성남시; asignBdgtAmt=500029000; bsnsDivNm=물품; chgDt=2025-06-02 11:03:32; dlvrDaynum=50; opninRgstClseDt=2025-06-07 23:59:00; orderInsttNm=경기도 성남시; prdctDtlList=[1^4511161601^비디오프로젝터]; rcptDt=2025-06-02 11:03:32; refNo=기업혁신과-1115; rgstDt=2025-06-02 11:03:29; specDocFileUrl1=https://www.g2b.go.kr/pn/pnz/pnza/UntyAtchFile/downloadFile.do?bfSpecRegNo=R25BD00075622&fileType=BFDTL&fileSeq=1; specDocFileUrl2=https://www.g2b.go.kr/pn/pnz/pnza/UntyAtchFile/downloadFile.do?bfSpecRegNo=R25BD00075622&fileType=BFDTL&fileSeq=2; swBizObjYn=N.",
      "hash": "sha256:ded9f2479927a2c1ffc9b7eb79d31e28242d4231041b4242c09fb5ed6f3336de",
      "source_path": "backfill_hrcsp_ssstndrd_info/raw/getPublicPrcureThngInfoThng/2025-06/page_00001.json"
    },
    {
      "source_line": 4729,
      "chunk_id": "chunk:g2b:sentence:7637555d6d2b4bcca9624867",
      "evidence_id": "evidence:g2b:sentence:row:d527dff46353b8c7e77540d4",
      "document_id": "doc:g2b:source:7b163281f6da85630a69aafe",
      "service": "backfill_hrcsp_ssstndrd_info",
      "operation": "getPublicPrcureThngInfoThng",
      "source_file": "backfill_hrcsp_ssstndrd_info/raw/getPublicPrcureThngInfoThng/2025-06/page_00001.json",
      "text": "G2B public OpenAPI row. service=backfill_hrcsp_ssstndrd_info. operation=getPublicPrcureThngInfoThng. source_file=raw/getPublicPrcureThngInfoThng/2025-06/page_00001.json. row_index=59. bfSpecRgstNo=R25BD00075624; bidNtceNoList=R25BK00881358; ofclNm=이종찬; ofclTelNo=043-290-8338; prdctClsfcNoNm=청주교도소 급식용 공산품 구매 입찰 공고; rlDminsttNm=법무부 대전지방교정청 청주교도소; asignBdgtAmt=219393910; bsnsDivNm=물품; chgDt=2025-06-02 11:04:26; dlvrDaynum=0; dlvrTmlmtDt=2025-09-30 00:00:00; opninRgstClseDt=2025-06-07 23:59:00; orderInsttNm=법무부 대전지방교정청 청주교도소; prdctDtlList=[1^5011209901^식육가공품]; rcptDt=2025-06-02 11:04:26; refNo=청주교도소 공고 제2025-20호; rgstDt=2025-06-02 11:04:23; specDocFileUrl1=https://www.g2b.go.kr/pn/pnz/pnza/UntyAtchFile/downloadFile.do?bfSpecRegNo=R25BD00075624&fileType=BFDTL&fileSeq=1; swBizObjYn=N.",
      "hash": "sha256:21c2388a254b25a0def8d1fe4edc42b093208f151b2f4813f4edd12608096e1e",
      "source_path": "backfill_hrcsp_ssstndrd_info/raw/getPublicPrcureThngInfoThng/2025-06/page_00001.json"
    },
    {
      "source_line": 4730,
      "chunk_id": "chunk:g2b:sentence:57569735ee24ecfd6124bddb",
      "evidence_id": "evidence:g2b:sentence:row:2c6151d4c7637e48dcfc9d1c",
      "document_id": "doc:g2b:source:7b163281f6da85630a69aafe",
      "service": "backfill_hrcsp_ssstndrd_info",
      "operation": "getPublicPrcureThngInfoThng",
      "source_file": "backfill_hrcsp_ssstndrd_info/raw/getPublicPrcureThngInfoThng/2025-06/page_00001.json",
      "text": "G2B public OpenAPI row. service=backfill_hrcsp_ssstndrd_info. operation=getPublicPrcureThngInfoThng. source_file=raw/getPublicPrcureThngInfoThng/2025-06/page_00001.json. row_index=60. bfSpecRgstNo=R25BD00075626; bidNtceNoList=R25BK00885861; ofclNm=홍석원; ofclTelNo=02-2610-1993; prdctClsfcNoNm=부트캠프사업 반도체전자공학과 Cadence Virtuoso 갱신; rlDminsttNm=동양미래대학교 산학협력단; asignBdgtAmt=31000000; bsnsDivNm=물품; chgDt=2025-06-02 11:06:40; dlvrDaynum=30; opninRgstClseDt=2025-06-07 23:59:00; orderInsttNm=동양미래대학교 산학협력단; prdctDtlList=[1^8610169601^기타교육서비스]; rcptDt=2025-06-02 11:06:40; refNo=산단 제2025-00호; rgstDt=2025-06-02 11:06:38; specDocFileUrl1=https://www.g2b.go.kr/pn/pnz/pnza/UntyAtchFile/downloadFile.do?bfSpecRegNo=R25BD00075626&fileType=BFDTL&fileSeq=1; swBizObjYn=N.",
      "hash": "sha256:895362dfef2563070f546a3886b82cfe7f5742d5d224543c7ae375f05a6aca16",
      "source_path": "backfill_hrcsp_ssstndrd_info/raw/getPublicPrcureThngInfoThng/2025-06/page_00001.json"
    },
    {
      "source_line": 4731,
      "chunk_id": "chunk:g2b:sentence:b1fae7c868afe4c500a189e5",
      "evidence_id": "evidence:g2b:sentence:row:f5a5804841008faf3d6e50cc",
      "document_id": "doc:g2b:source:7b163281f6da85630a69aafe",
      "service": "backfill_hrcsp_ssstndrd_info",
      "operation": "getPublicPrcureThngInfoThng",
      "source_file": "backfill_hrcsp_ssstndrd_info/raw/getPublicPrcureThngInfoThng/2025-06/page_00001.json",
      "text": "G2B public OpenAPI row. service=backfill_hrcsp_ssstndrd_info. operation=getPublicPrcureThngInfoThng. source_file=raw/getPublicPrcureThngInfoThng/2025-06/page_00001.json. row_index=61. bfSpecRgstNo=R25BD00075636; bidNtceNoList=R25BK00893360; ofclNm=김현식; prdctClsfcNoNm=2025년 화성외국인보호소 급식용 축산물 구매; rlDminsttNm=법무부 화성외국인보호소; asignBdgtAmt=85796303; bsnsDivNm=물품; chgDt=2025-06-02 11:13:21; dlvrDaynum=0; dlvrTmlmtDt=2026-06-30 00:00:00; opninRgstClseDt=2025-06-07 23:59:00; orderInsttNm=법무부 화성외국인보호소; prdctDtlList=[1^5011159801^식육류]; rcptDt=2025-06-02 11:13:21; refNo=관리과-2966; rgstDt=2025-06-02 11:13:18; specDocFileUrl1=https://www.g2b.go.kr/pn/pnz/pnza/UntyAtchFile/downloadFile.do?bfSpecRegNo=R25BD00075636&fileType=BFDTL&fileSeq=1; swBizObjYn=N.",
      "hash": "sha256:3d73b4a754437a450c9e7617cce5689dcf78e5a0cf5969f2c1ab496e931525d8",
      "source_path": "backfill_hrcsp_ssstndrd_info/raw/getPublicPrcureThngInfoThng/2025-06/page_00001.json"
    },
    {
      "source_line": 4732,
      "chunk_id": "chunk:g2b:sentence:420fbc62e2ebdf077119d44e",
      "evidence_id": "evidence:g2b:sentence:row:65a2711e77a3c9c336b8a0d3",
      "document_id": "doc:g2b:source:7b163281f6da85630a69aafe",
      "service": "backfill_hrcsp_ssstndrd_info",
      "operation": "getPublicPrcureThngInfoThng",
      "source_file": "backfill_hrcsp_ssstndrd_info/raw/getPublicPrcureThngInfoThng/2025-06/page_00001.json",
      "text": "G2B public OpenAPI row. service=backfill_hrcsp_ssstndrd_info. operation=getPublicPrcureThngInfoThng. source_file=raw/getPublicPrcureThngInfoThng/2025-06/page_00001.json. row_index=62. bfSpecRgstNo=R25BD00075638; bidNtceNoList=R25BK00889861; ofclNm=강명준; ofclTelNo=063-562-9705; prdctClsfcNoNm=전북인공지능고등학교 AI 교실 구축 및 기자재 구매; rlDminsttNm=전북특별자치도교육청 전북인공지능고등학교; asignBdgtAmt=247302000; bsnsDivNm=물품; chgDt=2025-06-02 11:14:24; dlvrDaynum=30; opninRgstClseDt=2025-06-07 23:59:00; orderInsttNm=전북특별자치도교육청 전북인공지능고등학교; prdctDtlList=[1^6010999901^교육훈련장비]; rcptDt=2025-06-02 11:14:24; refNo=20250602; rgstDt=2025-06-02 11:14:17; specDocFileUrl1=https://www.g2b.go.kr/pn/pnz/pnza/UntyAtchFile/downloadFile.do?bfSpecRegNo=R25BD00075638&fileType=BFDTL&fileSeq=1; specDocFileUrl2=https://www.g2b.go.kr/pn/pnz/pnza/UntyAtchFile/downloadFile.do?bfSpecRegNo=R25BD00075638&fileType=BFDTL&fileSeq=2; swBizObjYn=Y.",
      "hash": "sha256:4809de4fb9f6851b4c74ca4c5deec9682bab92dfd53d4522e3700e5c2bec8612",
      "source_path": "backfill_hrcsp_ssstndrd_info/raw/getPublicPrcureThngInfoThng/2025-06/page_00001.json"
    },
    {
      "source_line": 4733,
      "chunk_id": "chunk:g2b:sentence:d1ae4875f9f10b1dcc9bebd3",
      "evidence_id": "evidence:g2b:sentence:row:43c61da95fd16d9841ae4cec",
      "document_id": "doc:g2b:source:7b163281f6da85630a69aafe",
      "service": "backfill_hrcsp_ssstndrd_info",
      "operation": "getPublicPrcureThngInfoThng",
      "source_file": "backfill_hrcsp_ssstndrd_info/raw/getPublicPrcureThngInfoThng/2025-06/page_00001.json",
      "text": "G2B public OpenAPI row. service=backfill_hrcsp_ssstndrd_info. operation=getPublicPrcureThngInfoThng. source_file=raw/getPublicPrcureThngInfoThng/2025-06/page_00001.json. row_index=63. bfSpecRgstNo=R25BD00075643; bidNtceNoList=R25BK00901683; ofclNm=김태희; ofclTelNo=070-4056-8327; prdctClsfcNoNm=유세포분석기 구매; rlDminsttNm=주식회사 인게니움테라퓨틱스; asignBdgtAmt=181342400; bsnsDivNm=물품; chgDt=2025-06-02 11:19:38; dlvrDaynum=60; opninRgstClseDt=2025-06-07 23:59:00; orderInsttNm=조달청 대전지방조달청; prdctDtlList=[1^4111541301^세포분석기]; rcptDt=2025-06-02 11:19:38; refNo=IGT-P0028496; rgstDt=2025-06-02 11:19:37; specDocFileUrl1=https://www.g2b.go.kr/pn/pnz/pnza/UntyAtchFile/downloadFile.do?bfSpecRegNo=R25BD00075643&fileType=BFDTL&fileSeq=1; specDocFileUrl2=https://www.g2b.go.kr/pn/pnz/pnza/UntyAtchFile/downloadFile.do?bfSpecRegNo=R25BD00075643&fileType=BFDTL&fileSeq=2; swBizObjYn=N.",
      "hash": "sha256:db77cff556ee11b3910edb3b746a75bb01b10483f29038b65cc37a21bd873839",
      "source_path": "backfill_hrcsp_ssstndrd_info/raw/getPublicPrcureThngInfoThng/2025-06/page_00001.json"
    },
    {
      "source_line": 4734,
      "chunk_id": "chunk:g2b:sentence:285206d195e1b029537026e3",
      "evidence_id": "evidence:g2b:sentence:row:47b365e1f4f7537d72785862",
      "document_id": "doc:g2b:source:7b163281f6da85630a69aafe",
      "service": "backfill_hrcsp_ssstndrd_info",
      "operation": "getPublicPrcureThngInfoThng",
      "source_file": "backfill_hrcsp_ssstndrd_info/raw/getPublicPrcureThngInfoThng/2025-06/page_00001.json",
      "text": "G2B public OpenAPI row. service=backfill_hrcsp_ssstndrd_info. operation=getPublicPrcureThngInfoThng. source_file=raw/getPublicPrcureThngInfoThng/2025-06/page_00001.json. row_index=64. bfSpecRgstNo=R25BD00075644; prdctClsfcNoNm='25년 대테러장비(고배율관측경) 구매; rlDminsttNm=국방부 육군군수사령부; asignBdgtAmt=70000000; bsnsDivNm=물품; dlvrDaynum=0; opninRgstClseDt=2025-06-06 00:00:00; orderInsttNm=국방부 육군군수사령부; prdctDtlList=[1^^&apos;25년 대테러장비(고배율관측경) 구매]; rcptDt=2025-06-02 11:20:01; refNo=PS2025LCF22363; rgstDt=2025-06-02 11:20:01; swBizObjYn=N.",
      "hash": "sha256:50597284408e6262d939bc7f09085aca01d637d2957223b9c9cbed8c2efd4af7",
      "source_path": "backfill_hrcsp_ssstndrd_info/raw/getPublicPrcureThngInfoThng/2025-06/page_00001.json"
    },
    {
      "source_line": 4735,
      "chunk_id": "chunk:g2b:sentence:765944e1120ec8ee180a15f6",
      "evidence_id": "evidence:g2b:sentence:row:ab95e016b488c9df2b56ff6d",
      "document_id": "doc:g2b:source:7b163281f6da85630a69aafe",
      "service": "backfill_hrcsp_ssstndrd_info",
      "operation": "getPublicPrcureThngInfoThng",
      "source_file": "backfill_hrcsp_ssstndrd_info/raw/getPublicPrcureThngInfoThng/2025-06/page_00001.json",
      "text": "G2B public OpenAPI row. service=backfill_hrcsp_ssstndrd_info. operation=getPublicPrcureThngInfoThng. source_file=raw/getPublicPrcureThngInfoThng/2025-06/page_00001.json. row_index=65. bfSpecRgstNo=R25BD00075645; bidNtceNoList=R25BK01039096,R25BK00910959,R25BK00960275; ofclNm=박병주; ofclTelNo=070-4056-8374; prdctClsfcNoNm=2025년 교정기관 원격의료시스템 노후장비 교체; rlDminsttNm=법무부 대전지방교정청; asignBdgtAmt=395967120; bsnsDivNm=물품; chgDt=2025-06-02 13:20:47; dlvrDaynum=90; opninRgstClseDt=2025-06-07 23:59:00; orderInsttNm=조달청 대전지방조달청; prdctDtlList=[1^4220360601^원격진료시스템]; rcptDt=2025-06-02 11:20:21; refNo=대전지방교정청 입찰 제2025-11호; rgstDt=2025-06-02 11:20:20; specDocFileUrl1=https://www.g2b.go.kr/pn/pnz/pnza/UntyAtchFile/downloadFile.do?bfSpecRegNo=R25BD00075645&fileType=BFDTL&fileSeq=1; swBizObjYn=N.",
      "hash": "sha256:55f975cb9df79bf1c4e086850164bdd587d1832636d9d2aabbd0017ef11a52e7",
      "source_path": "backfill_hrcsp_ssstndrd_info/raw/getPublicPrcureThngInfoThng/2025-06/page_00001.json"
    },
    {
      "source_line": 4736,
      "chunk_id": "chunk:g2b:sentence:a3d7fb2e3b04bf71c338f1f4",
      "evidence_id": "evidence:g2b:sentence:row:053117d5df6ccf537da1047f",
      "document_id": "doc:g2b:source:7b163281f6da85630a69aafe",
      "service": "backfill_hrcsp_ssstndrd_info",
      "operation": "getPublicPrcureThngInfoThng",
      "source_file": "backfill_hrcsp_ssstndrd_info/raw/getPublicPrcureThngInfoThng/2025-06/page_00001.json",
      "text": "G2B public OpenAPI row. service=backfill_hrcsp_ssstndrd_info. operation=getPublicPrcureThngInfoThng. source_file=raw/getPublicPrcureThngInfoThng/2025-06/page_00001.json. row_index=66. bfSpecRgstNo=R25BD00075646; bidNtceNoList=R25BK00900908; ofclNm=함순형; ofclTelNo=032-453-7164; prdctClsfcNoNm=송도하수처리장 2단계 기전설비 증설사업 기계공사-오수처리용산기장치; rlDminsttNm=인천광역시 경제자유구역청; asignBdgtAmt=74432000; bsnsDivNm=물품; chgDt=2025-06-02 11:20:33; dlvrDaynum=0; dlvrTmlmtDt=2025-10-31 00:00:00; opninRgstClseDt=2025-06-07 23:59:00; orderInsttNm=인천광역시 경제자유구역청; prdctDtlList=[1^4710996401^오수처리용산기장치]; rcptDt=2025-06-02 11:20:33; refNo=운영지원과-10607; rgstDt=2025-06-02 11:20:30; specDocFileUrl1=https://www.g2b.go.kr/pn/pnz/pnza/UntyAtchFile/downloadFile.do?bfSpecRegNo=R25BD00075646&fileType=BFDTL&fileSeq=1; specDocFileUrl2=https://www.g2b.go.kr/pn/pnz/pnza/UntyAtchFile/downloadFile.do?bfSpecRegNo=R25BD00075646&fileType=BFDTL&fileSeq=2; specDocFileUrl3=https://www.g2b.go.kr/pn/pnz/pnza/UntyAtchFile/downloadFile.do?bfSpecRegNo=R25BD00075646&fileType=BFDTL&fileSeq=3; specDocFileUrl4=https://www.g2b.go.kr/pn/pnz/pnza/UntyAtchFile/downloadFile.do?bfSpecRegNo=R25BD00075646&fileType=BFDTL&fileSeq=4; swBizObjYn=N.",
      "hash": "sha256:6e738c9d9951c4c1ffc3e0e83d603da95a039e24e3706a2abb6bbf535260acec",
      "source_path": "backfill_hrcsp_ssstndrd_info/raw/getPublicPrcureThngInfoThng/2025-06/page_00001.json"
    },
    {
      "source_line": 4737,
      "chunk_id": "chunk:g2b:sentence:1b8ac3e49d8558f45d3244de",
      "evidence_id": "evidence:g2b:sentence:row:ebd47008d940b34ccb7ed25f",
      "document_id": "doc:g2b:source:7b163281f6da85630a69aafe",
      "service": "backfill_hrcsp_ssstndrd_info",
      "operation": "getPublicPrcureThngInfoThng",
      "source_file": "backfill_hrcsp_ssstndrd_info/raw/getPublicPrcureThngInfoThng/2025-06/page_00001.json",
      "text": "G2B public OpenAPI row. service=backfill_hrcsp_ssstndrd_info. operation=getPublicPrcureThngInfoThng. source_file=raw/getPublicPrcureThngInfoThng/2025-06/page_00001.json. row_index=67. bfSpecRgstNo=R25BD00075649; bidNtceNoList=R25BK00905534; ofclNm=윤순제; ofclTelNo=070-4056-8421; prdctClsfcNoNm=건식실리콘식각장치 구매; rlDminsttNm=강원대학교 산학협력단; asignBdgtAmt=704060160; bsnsDivNm=물품; chgDt=2025-06-02 11:21:42; dlvrDaynum=150; opninRgstClseDt=2025-06-07 23:59:00; orderInsttNm=조달청 강원지방조달청; prdctDtlList=[1^2321118001^웨이퍼식각기]; rcptDt=2025-06-02 11:21:42; refNo=2025-0516-001; rgstDt=2025-06-02 11:21:41; specDocFileUrl1=https://www.g2b.go.kr/pn/pnz/pnza/UntyAtchFile/downloadFile.do?bfSpecRegNo=R25BD00075649&fileType=BFDTL&fileSeq=1; swBizObjYn=N.",
      "hash": "sha256:e64c9276ac9f902dde05c43331d64085260f05c31fc13c99e1529de3d9b8355e",
      "source_path": "backfill_hrcsp_ssstndrd_info/raw/getPublicPrcureThngInfoThng/2025-06/page_00001.json"
    },
    {
      "source_line": 4738,
      "chunk_id": "chunk:g2b:sentence:b955dfa68bd2ea94d855598e",
      "evidence_id": "evidence:g2b:sentence:row:d320432e07372cf1af75893b",
      "document_id": "doc:g2b:source:7b163281f6da85630a69aafe",
      "service": "backfill_hrcsp_ssstndrd_info",
      "operation": "getPublicPrcureThngInfoThng",
      "source_file": "backfill_hrcsp_ssstndrd_info/raw/getPublicPrcureThngInfoThng/2025-06/page_00001.json",
      "text": "G2B public OpenAPI row. service=backfill_hrcsp_ssstndrd_info. operation=getPublicPrcureThngInfoThng. source_file=raw/getPublicPrcureThngInfoThng/2025-06/page_00001.json. row_index=68. bfSpecRgstNo=R25BD00075651; bidNtceNoList=R25BK00898271,R25BK00930984; ofclNm=김갑수; ofclTelNo=070-4056-6742; prdctClsfcNoNm=고속국도 제14호선 함양울산선(합천-창녕) 건설공사 제9공구 레미콘 구매; rlDminsttNm=한국도로공사합천창녕건설사업단; asignBdgtAmt=550390150; bsnsDivNm=물품; chgDt=2025-06-02 11:22:54; dlvrDaynum=0; dlvrTmlmtDt=2025-12-31 00:00:00; opninRgstClseDt=2025-06-09 23:59:00; orderInsttNm=조달청 경남지방조달청; prdctDtlList=[1^3011150501^레미콘],[2^3011150501^레미콘],[3^3011150501^레미콘],[4^3011150501^레미콘],[5^3011150501^레미콘]; rcptDt=2025-06-02 11:22:54; refNo=합창 공사관리부 1153; rgstDt=2025-06-02 11:22:52; specDocFileUrl1=https://www.g2b.go.kr/pn/pnz/pnza/UntyAtchFile/downloadFile.do?bfSpecRegNo=R25BD00075651&fileType=BFDTL&fileSeq=1; swBizObjYn=N.",
      "hash": "sha256:0b3d9b5796c124a846503f195094069f3362a39dd26a17c3c204dd7f8795f91c",
      "source_path": "backfill_hrcsp_ssstndrd_info/raw/getPublicPrcureThngInfoThng/2025-06/page_00001.json"
    },
    {
      "source_line": 4739,
      "chunk_id": "chunk:g2b:sentence:ab9124f49d5da4bd8e46d117",
      "evidence_id": "evidence:g2b:sentence:row:c100cd31ec9cf16e6439384e",
      "document_id": "doc:g2b:source:7b163281f6da85630a69aafe",
      "service": "backfill_hrcsp_ssstndrd_info",
      "operation": "getPublicPrcureThngInfoThng",
      "source_file": "backfill_hrcsp_ssstndrd_info/raw/getPublicPrcureThngInfoThng/2025-06/page_00001.json",
      "text": "G2B public OpenAPI row. service=backfill_hrcsp_ssstndrd_info. operation=getPublicPrcureThngInfoThng. source_file=raw/getPublicPrcureThngInfoThng/2025-06/page_00001.json. row_index=69. bfSpecRgstNo=R25BD00075652; bidNtceNoList=R25BK00901136; ofclNm=함순형; ofclTelNo=032-453-7164; prdctClsfcNoNm=송도하수처리장 2단계 기전설비 증설사업 기계공사-전동식와이어로프호이스트; rlDminsttNm=인천광역시 경제자유구역청; asignBdgtAmt=98230000; bsnsDivNm=물품; chgDt=2025-06-02 11:23:53; dlvrDaynum=0; dlvrTmlmtDt=2025-11-28 00:00:00; opninRgstClseDt=2025-06-07 23:59:00; orderInsttNm=인천광역시 경제자유구역청; prdctDtlList=[1^2410160201^전동식와이어로프호이스트]; rcptDt=2025-06-02 11:23:53; refNo=운영지원과-10605; rgstDt=2025-06-02 11:23:42; specDocFileUrl1=https://www.g2b.go.kr/pn/pnz/pnza/UntyAtchFile/downloadFile.do?bfSpecRegNo=R25BD00075652&fileType=BFDTL&fileSeq=1; specDocFileUrl2=https://www.g2b.go.kr/pn/pnz/pnza/UntyAtchFile/downloadFile.do?bfSpecRegNo=R25BD00075652&fileType=BFDTL&fileSeq=2; specDocFileUrl3=https://www.g2b.go.kr/pn/pnz/pnza/UntyAtchFile/downloadFile.do?bfSpecRegNo=R25BD00075652&fileType=BFDTL&fileSeq=3; specDocFileUrl4=https://www.g2b.go.kr/pn/pnz/pnza/UntyAtchFile/downloadFile.do?bfSpecRegNo=R25BD00075652&fileType=BFDTL&fileSeq=4; swBizObjYn=N.",
      "hash": "sha256:99930b86e74c489800b8ad47bde6b464ba4bc5d5fd9373bcb3167655f731849d",
      "source_path": "backfill_hrcsp_ssstndrd_info/raw/getPublicPrcureThngInfoThng/2025-06/page_00001.json"
    },
    {
      "source_line": 4740,
      "chunk_id": "chunk:g2b:sentence:7c3b453bd42619ad65e91116",
      "evidence_id": "evidence:g2b:sentence:row:ac5f54c429a45a5563715204",
      "document_id": "doc:g2b:source:7b163281f6da85630a69aafe",
      "service": "backfill_hrcsp_ssstndrd_info",
      "operation": "getPublicPrcureThngInfoThng",
      "source_file": "backfill_hrcsp_ssstndrd_info/raw/getPublicPrcureThngInfoThng/2025-06/page_00001.json",
      "text": "G2B public OpenAPI row. service=backfill_hrcsp_ssstndrd_info. operation=getPublicPrcureThngInfoThng. source_file=raw/getPublicPrcureThngInfoThng/2025-06/page_00001.json. row_index=70. bfSpecRgstNo=R25BD00075653; prdctClsfcNoNm=(일장) 교량가설단정 브러시 등 33종 구매; rlDminsttNm=육군종합정비창; asignBdgtAmt=38578841; bsnsDivNm=물품; dlvrDaynum=0; opninRgstClseDt=2025-06-04 00:00:00; orderInsttNm=육군종합정비창; prdctDtlList=[1^^(일장) 교량가설단정 브러시 등 33종 구매]; rcptDt=2025-06-02 11:25:01; refNo=PS2025LDH22388; rgstDt=2025-06-02 11:25:01; swBizObjYn=N.",
      "hash": "sha256:9d92bf9060c8169b351bfb9a037cd61f0e4f1f823143463cd6f3e89924804921",
      "source_path": "backfill_hrcsp_ssstndrd_info/raw/getPublicPrcureThngInfoThng/2025-06/page_00001.json"
    },
    {
      "source_line": 4741,
      "chunk_id": "chunk:g2b:sentence:be9b18133a9856a1330af1f6",
      "evidence_id": "evidence:g2b:sentence:row:104a2547c9c4c56d63c43f4d",
      "document_id": "doc:g2b:source:7b163281f6da85630a69aafe",
      "service": "backfill_hrcsp_ssstndrd_info",
      "operation": "getPublicPrcureThngInfoThng",
      "source_file": "backfill_hrcsp_ssstndrd_info/raw/getPublicPrcureThngInfoThng/2025-06/page_00001.json",
      "text": "G2B public OpenAPI row. service=backfill_hrcsp_ssstndrd_info. operation=getPublicPrcureThngInfoThng. source_file=raw/getPublicPrcureThngInfoThng/2025-06/page_00001.json. row_index=71. bfSpecRgstNo=R25BD00075654; bidNtceNoList=R25BK00902497,R25BK00963620; ofclNm=황준배; ofclTelNo=070-4056-7977; prdctClsfcNoNm=컴퓨터서버 구매; rlDminsttNm=국가첨단백신개발센터; asignBdgtAmt=132351230; bsnsDivNm=물품; chgDt=2025-06-02 11:27:55; dlvrDaynum=60; opninRgstClseDt=2025-06-07 23:59:00; orderInsttNm=조달청 대구지방조달청; prdctDtlList=[1^4321150102^컴퓨터서버]; rcptDt=2025-06-02 11:27:55; refNo=운영지원팀-1347; rgstDt=2025-06-02 11:27:54; specDocFileUrl1=https://www.g2b.go.kr/pn/pnz/pnza/UntyAtchFile/downloadFile.do?bfSpecRegNo=R25BD00075654&fileType=BFDTL&fileSeq=1; specDocFileUrl2=https://www.g2b.go.kr/pn/pnz/pnza/UntyAtchFile/downloadFile.do?bfSpecRegNo=R25BD00075654&fileType=BFDTL&fileSeq=2; swBizObjYn=N.",
      "hash": "sha256:4d5f1169069c9c721f2e9cd22e3624f98aeccf95a86ca503ad4409f482205eac",
      "source_path": "backfill_hrcsp_ssstndrd_info/raw/getPublicPrcureThngInfoThng/2025-06/page_00001.json"
    },
    {
      "source_line": 4742,
      "chunk_id": "chunk:g2b:sentence:5178378a52e57c3d7ed5ded5",
      "evidence_id": "evidence:g2b:sentence:row:37da3b2b70afabd5633ffa6f",
      "document_id": "doc:g2b:source:7b163281f6da85630a69aafe",
      "service": "backfill_hrcsp_ssstndrd_info",
      "operation": "getPublicPrcureThngInfoThng",
      "source_file": "backfill_hrcsp_ssstndrd_info/raw/getPublicPrcureThngInfoThng/2025-06/page_00001.json",
      "text": "G2B public OpenAPI row. service=backfill_hrcsp_ssstndrd_info. operation=getPublicPrcureThngInfoThng. source_file=raw/getPublicPrcureThngInfoThng/2025-06/page_00001.json. row_index=72. bfSpecRgstNo=R25BD00075657; bidNtceNoList=R25BK00889290; ofclNm=성지은; prdctClsfcNoNm=「빈집정비통합지원시스템  AI서버 구매 」; rlDminsttNm=한국부동산원; asignBdgtAmt=194000000; bsnsDivNm=물품; chgDt=2025-06-02 11:29:53; dlvrDaynum=90; opninRgstClseDt=2025-06-07 23:59:00; orderInsttNm=한국부동산원; prdctDtlList=[1^4321150102^컴퓨터서버]; rcptDt=2025-06-02 11:29:53; refNo=ICT센터-11291; rgstDt=2025-06-02 11:29:50; specDocFileUrl1=https://www.g2b.go.kr/pn/pnz/pnza/UntyAtchFile/downloadFile.do?bfSpecRegNo=R25BD00075657&fileType=BFDTL&fileSeq=1; specDocFileUrl2=https://www.g2b.go.kr/pn/pnz/pnza/UntyAtchFile/downloadFile.do?bfSpecRegNo=R25BD00075657&fileType=BFDTL&fileSeq=2; swBizObjYn=Y.",
      "hash": "sha256:00b07d5824c157d08db8913af5bc61ab0747326ca7141208b649199f22aa34a2",
      "source_path": "backfill_hrcsp_ssstndrd_info/raw/getPublicPrcureThngInfoThng/2025-06/page_00001.json"
    },
    {
      "source_line": 4743,
      "chunk_id": "chunk:g2b:sentence:2b0864bf282369a2381b9f7b",
      "evidence_id": "evidence:g2b:sentence:row:b9b30a62a365a37c475bdd8c",
      "document_id": "doc:g2b:source:7b163281f6da85630a69aafe",
      "service": "backfill_hrcsp_ssstndrd_info",
      "operation": "getPublicPrcureThngInfoThng",
      "source_file": "backfill_hrcsp_ssstndrd_info/raw/getPublicPrcureThngInfoThng/2025-06/page_00001.json",
      "text": "G2B public OpenAPI row. service=backfill_hrcsp_ssstndrd_info. operation=getPublicPrcureThngInfoThng. source_file=raw/getPublicPrcureThngInfoThng/2025-06/page_00001.json. row_index=73. bfSpecRgstNo=R25BD00075659; bidNtceNoList=R25BK00927145; ofclNm=황준배; ofclTelNo=070-4056-7977; prdctClsfcNoNm=경상북도교육청 예천도서관 ICT 및 RFID 시스템 구축 계약요청; rlDminsttNm=경상북도교육청 경상북도예천교육지원청; asignBdgtAmt=648038500; bsnsDivNm=물품; chgDt=2025-06-02 11:30:12; dlvrDaynum=90; opninRgstClseDt=2025-06-07 23:59:00; orderInsttNm=조달청 대구지방조달청; prdctDtlList=[1^4321179701^도서관리시스템]; rcptDt=2025-06-02 11:30:12; refNo=행정지원과-10746; rgstDt=2025-06-02 11:30:10; specDocFileUrl1=https://www.g2b.go.kr/pn/pnz/pnza/UntyAtchFile/downloadFile.do?bfSpecRegNo=R25BD00075659&fileType=BFDTL&fileSeq=1; swBizObjYn=Y.",
      "hash": "sha256:ee15ffd9005a6ecfe3ba13cadb6a197b3365b3872fe9d5518aef66af6a390002",
      "source_path": "backfill_hrcsp_ssstndrd_info/raw/getPublicPrcureThngInfoThng/2025-06/page_00001.json"
    },
    {
      "source_line": 4744,
      "chunk_id": "chunk:g2b:sentence:ad63a0b06d78720d9f85c051",
      "evidence_id": "evidence:g2b:sentence:row:3589f285ef72f921f4c0c95c",
      "document_id": "doc:g2b:source:7b163281f6da85630a69aafe",
      "service": "backfill_hrcsp_ssstndrd_info",
      "operation": "getPublicPrcureThngInfoThng",
      "source_file": "backfill_hrcsp_ssstndrd_info/raw/getPublicPrcureThngInfoThng/2025-06/page_00001.json",
      "text": "G2B public OpenAPI row. service=backfill_hrcsp_ssstndrd_info. operation=getPublicPrcureThngInfoThng. source_file=raw/getPublicPrcureThngInfoThng/2025-06/page_00001.json. row_index=74. bfSpecRgstNo=R25BD00075664; bidNtceNoList=R25BK00895198; ofclNm=박지수; ofclTelNo=042-715-6055; prdctClsfcNoNm=2025년 대전환경조합 청소차량 수직형 배출가스 배기관 설치; rlDminsttNm=대전환경사업지방자치단체조합; asignBdgtAmt=204000000; bsnsDivNm=물품; chgDt=2025-06-02 11:42:06; dlvrDaynum=120; opninRgstClseDt=2025-06-07 23:59:00; orderInsttNm=대전환경사업지방자치단체조합; prdctDtlList=[1^2522130801^디젤동차용배기다기관]; rcptDt=2025-06-02 11:42:06; refNo=277-83-00049; rgstDt=2025-06-02 11:42:04; specDocFileUrl1=https://www.g2b.go.kr/pn/pnz/pnza/UntyAtchFile/downloadFile.do?bfSpecRegNo=R25BD00075664&fileType=BFDTL&fileSeq=1; specDocFileUrl2=https://www.g2b.go.kr/pn/pnz/pnza/UntyAtchFile/downloadFile.do?bfSpecRegNo=R25BD00075664&fileType=BFDTL&fileSeq=2; swBizObjYn=N.",
      "hash": "sha256:c306152dcba3c770dd613006077f24c2181546b58050c153aead8e2fa4555d2a",
      "source_path": "backfill_hrcsp_ssstndrd_info/raw/getPublicPrcureThngInfoThng/2025-06/page_00001.json"
    },
    {
      "source_line": 4745,
      "chunk_id": "chunk:g2b:sentence:923a8d4037ad1bc841951a60",
      "evidence_id": "evidence:g2b:sentence:row:8f73bbbf66b65eb6f8550654",
      "document_id": "doc:g2b:source:7b163281f6da85630a69aafe",
      "service": "backfill_hrcsp_ssstndrd_info",
      "operation": "getPublicPrcureThngInfoThng",
      "source_file": "backfill_hrcsp_ssstndrd_info/raw/getPublicPrcureThngInfoThng/2025-06/page_00001.json",
      "text": "G2B public OpenAPI row. service=backfill_hrcsp_ssstndrd_info. operation=getPublicPrcureThngInfoThng. source_file=raw/getPublicPrcureThngInfoThng/2025-06/page_00001.json. row_index=75. bfSpecRgstNo=R25BD00075665; bidNtceNoList=R25BK00890333; ofclNm=김은희; ofclTelNo=053-243-6671; prdctClsfcNoNm=2025년 하반기 강동노인복지관 식자재(부식) 납품업체 입찰 공고; rlDminsttNm=강동노인복지관; asignBdgtAmt=1836750; bsnsDivNm=물품; chgDt=2025-06-02 11:55:37; dlvrDaynum=0; dlvrTmlmtDt=2025-12-31 00:00:00; opninRgstClseDt=2025-06-05 23:59:00; orderInsttNm=강동노인복지관; prdctDtlList=[1^1015150701^오이종자및묘목]; rcptDt=2025-06-02 11:55:37; refNo=8548200209; rgstDt=2025-06-02 11:55:32; specDocFileUrl1=https://www.g2b.go.kr/pn/pnz/pnza/UntyAtchFile/downloadFile.do?bfSpecRegNo=R25BD00075665&fileType=BFDTL&fileSeq=1; swBizObjYn=N.",
      "hash": "sha256:21ebd29fa6da89a8e964e6768a221c40657d6f422afeac8be9e0957041c82d82",
      "source_path": "backfill_hrcsp_ssstndrd_info/raw/getPublicPrcureThngInfoThng/2025-06/page_00001.json"
    },
    {
      "source_line": 4746,
      "chunk_id": "chunk:g2b:sentence:7bc46be0e2c7352ef84c5170",
      "evidence_id": "evidence:g2b:sentence:row:a05a3f28a66549b877da7fbf",
      "document_id": "doc:g2b:source:7b163281f6da85630a69aafe",
      "service": "backfill_hrcsp_ssstndrd_info",
      "operation": "getPublicPrcureThngInfoThng",
      "source_file": "backfill_hrcsp_ssstndrd_info/raw/getPublicPrcureThngInfoThng/2025-06/page_00001.json",
      "text": "G2B public OpenAPI row. service=backfill_hrcsp_ssstndrd_info. operation=getPublicPrcureThngInfoThng. source_file=raw/getPublicPrcureThngInfoThng/2025-06/page_00001.json. row_index=76. bfSpecRgstNo=R25BD00075673; bidNtceNoList=R25BK00881391,R25BK01130171,R25BK01113538,R25BK00960490; ofclNm=김애지; prdctClsfcNoNm=고성능 데이터 로깅 및 시스템; rlDminsttNm=주식회사 에이스웍스코리아; asignBdgtAmt=50000000; bsnsDivNm=물품; chgDt=2025-06-02 12:36:12; dlvrDaynum=30; opninRgstClseDt=2025-06-06 23:59:00; orderInsttNm=주식회사 에이스웍스코리아; prdctDtlList=[1^4320141601^데이터수집보드]; rcptDt=2025-06-02 12:36:12; refNo=R25DD20282823; rgstDt=2025-06-02 12:35:51; swBizObjYn=Y.",
      "hash": "sha256:b23f11ed0bfa73f8cfed839a9a897f08a4ff1064bae3145e07e181be3c896c23",
      "source_path": "backfill_hrcsp_ssstndrd_info/raw/getPublicPrcureThngInfoThng/2025-06/page_00001.json"
    },
    {
      "source_line": 4747,
      "chunk_id": "chunk:g2b:sentence:08f4dcca6669b4fff79532a4",
      "evidence_id": "evidence:g2b:sentence:row:672ff690912787efc8658212",
      "document_id": "doc:g2b:source:7b163281f6da85630a69aafe",
      "service": "backfill_hrcsp_ssstndrd_info",
      "operation": "getPublicPrcureThngInfoThng",
      "source_file": "backfill_hrcsp_ssstndrd_info/raw/getPublicPrcureThngInfoThng/2025-06/page_00001.json",
      "text": "G2B public OpenAPI row. service=backfill_hrcsp_ssstndrd_info. operation=getPublicPrcureThngInfoThng. source_file=raw/getPublicPrcureThngInfoThng/2025-06/page_00001.json. row_index=77. bfSpecRgstNo=R25BD00075677; bidNtceNoList=R25BK00954282; ofclNm=유승학; ofclTelNo=070-4056-8263; prdctClsfcNoNm=고흥2지구 풍수해생활권 종합정비사업 관급자재(잠수교 상부거더) 제작 설치; rlDminsttNm=전라남도 고흥군; asignBdgtAmt=414149310; bsnsDivNm=물품; chgDt=2025-06-02 13:02:47; dlvrDaynum=210; opninRgstClseDt=2025-06-07 23:59:00; orderInsttNm=조달청 광주지방조달청; prdctDtlList=[1^3010170405^I빔]; rcptDt=2025-06-02 13:02:47; refNo=재난안전과-6618; rgstDt=2025-06-02 13:02:45; specDocFileUrl1=https://www.g2b.go.kr/pn/pnz/pnza/UntyAtchFile/downloadFile.do?bfSpecRegNo=R25BD00075677&fileType=BFDTL&fileSeq=1; swBizObjYn=N.",
      "hash": "sha256:2b7ae01c2ccc9ef7e0afc6042b3ed5ef9b728aa354d1a2d225865a5c9395fe9d",
      "source_path": "backfill_hrcsp_ssstndrd_info/raw/getPublicPrcureThngInfoThng/2025-06/page_00001.json"
    },
    {
      "source_line": 4748,
      "chunk_id": "chunk:g2b:sentence:320296c4c9910f012168cbfb",
      "evidence_id": "evidence:g2b:sentence:row:b9338f42f34e442c9915d3c6",
      "document_id": "doc:g2b:source:7b163281f6da85630a69aafe",
      "service": "backfill_hrcsp_ssstndrd_info",
      "operation": "getPublicPrcureThngInfoThng",
      "source_file": "backfill_hrcsp_ssstndrd_info/raw/getPublicPrcureThngInfoThng/2025-06/page_00001.json",
      "text": "G2B public OpenAPI row. service=backfill_hrcsp_ssstndrd_info. operation=getPublicPrcureThngInfoThng. source_file=raw/getPublicPrcureThngInfoThng/2025-06/page_00001.json. row_index=78. bfSpecRgstNo=R25BD00075678; bidNtceNoList=R25BK00915802; ofclNm=유승학; ofclTelNo=070-4056-8263; prdctClsfcNoNm=화순 도암 도장교 재가설공사(2025년) SEB거더교 구매; rlDminsttNm=전라남도; asignBdgtAmt=1129646040; bsnsDivNm=물품; chgDt=2025-06-02 13:03:45; dlvrDaynum=0; dlvrTmlmtDt=2025-09-30 00:00:00; opninRgstClseDt=2025-06-07 23:59:00; orderInsttNm=조달청 광주지방조달청; prdctDtlList=[1^3010171701^콘크리트빔]; rcptDt=2025-06-02 13:03:45; refNo=도로정책과-3846; rgstDt=2025-06-02 13:03:43; specDocFileUrl1=https://www.g2b.go.kr/pn/pnz/pnza/UntyAtchFile/downloadFile.do?bfSpecRegNo=R25BD00075678&fileType=BFDTL&fileSeq=1; swBizObjYn=N.",
      "hash": "sha256:1d5705a0fa815c9c92400fea566686d3f88e621a4264cc9c6dccf44bb801f631",
      "source_path": "backfill_hrcsp_ssstndrd_info/raw/getPublicPrcureThngInfoThng/2025-06/page_00001.json"
    },
    {
      "source_line": 4749,
      "chunk_id": "chunk:g2b:sentence:7bafe69c73480e800debad9c",
      "evidence_id": "evidence:g2b:sentence:row:e0b493cab9d8cbc6883bb275",
      "document_id": "doc:g2b:source:7b163281f6da85630a69aafe",
      "service": "backfill_hrcsp_ssstndrd_info",
      "operation": "getPublicPrcureThngInfoThng",
      "source_file": "backfill_hrcsp_ssstndrd_info/raw/getPublicPrcureThngInfoThng/2025-06/page_00001.json",
      "text": "G2B public OpenAPI row. service=backfill_hrcsp_ssstndrd_info. operation=getPublicPrcureThngInfoThng. source_file=raw/getPublicPrcureThngInfoThng/2025-06/page_00001.json. row_index=79. bfSpecRgstNo=R25BD00075679; bidNtceNoList=R25BK00922359; ofclNm=고은아; ofclTelNo=043-830-5114; prdctClsfcNoNm=연풍면 기초생활거점조성사업 한식창호(목제창) 제조구매설치; rlDminsttNm=한국농어촌공사 충북지역본부 괴산.증평지사; asignBdgtAmt=137232000; bsnsDivNm=물품; chgDt=2025-06-02 13:05:38; dlvrDaynum=0; dlvrTmlmtDt=2025-12-19 00:00:00; opninRgstClseDt=2025-06-07 23:59:00; orderInsttNm=한국농어촌공사 충북지역본부 괴산.증평지사; prdctDtlList=[1^3017169601^목제창]; rcptDt=2025-06-02 13:05:38; refNo=괴산증평농지관리-3118; rgstDt=2025-06-02 13:05:35; specDocFileUrl1=https://www.g2b.go.kr/pn/pnz/pnza/UntyAtchFile/downloadFile.do?bfSpecRegNo=R25BD00075679&fileType=BFDTL&fileSeq=1; specDocFileUrl2=https://www.g2b.go.kr/pn/pnz/pnza/UntyAtchFile/downloadFile.do?bfSpecRegNo=R25BD00075679&fileType=BFDTL&fileSeq=2; specDocFileUrl3=https://www.g2b.go.kr/pn/pnz/pnza/UntyAtchFile/downloadFile.do?bfSpecRegNo=R25BD00075679&fileType=BFDTL&fileSeq=3; specDocFileUrl4=https://www.g2b.go.kr/pn/pnz/pnza/UntyAtchFile/downloadFile.do?bfSpecRegNo=R25BD00075679&fileType=BFDTL&fileSeq=4; swBizObjYn=N.",
      "hash": "sha256:c75232ef2b04d76c400f301c41e65dbd39fae58787fd7b1af12131005d4b4ad2",
      "source_path": "backfill_hrcsp_ssstndrd_info/raw/getPublicPrcureThngInfoThng/2025-06/page_00001.json"
    },
    {
      "source_line": 4750,
      "chunk_id": "chunk:g2b:sentence:272728f617a088ce92ef17f8",
      "evidence_id": "evidence:g2b:sentence:row:5a6949760e1212e9d6612f6c",
      "document_id": "doc:g2b:source:7b163281f6da85630a69aafe",
      "service": "backfill_hrcsp_ssstndrd_info",
      "operation": "getPublicPrcureThngInfoThng",
      "source_file": "backfill_hrcsp_ssstndrd_info/raw/getPublicPrcureThngInfoThng/2025-06/page_00001.json",
      "text": "G2B public OpenAPI row. service=backfill_hrcsp_ssstndrd_info. operation=getPublicPrcureThngInfoThng. source_file=raw/getPublicPrcureThngInfoThng/2025-06/page_00001.json. row_index=80. bfSpecRgstNo=R25BD00075685; bidNtceNoList=R25BK00905984; ofclNm=나단아; ofclTelNo=043-931-0683; prdctClsfcNoNm=2026학년도 대학수학능력시험 9월 모의평가 OMR 답안지 등 인쇄; rlDminsttNm=한국교육과정평가원; asignBdgtAmt=146000000; bsnsDivNm=물품; chgDt=2025-06-02 13:16:06; dlvrDaynum=0; dlvrTmlmtDt=2025-08-08 00:00:00; opninRgstClseDt=2025-06-07 23:59:00; orderInsttNm=한국교육과정평가원; prdctDtlList=[1^1411150601^전산디자인]; rcptDt=2025-06-02 13:16:06; refNo=구매계약부-2212; rgstDt=2025-06-02 13:16:04; specDocFileUrl1=https://www.g2b.go.kr/pn/pnz/pnza/UntyAtchFile/downloadFile.do?bfSpecRegNo=R25BD00075685&fileType=BFDTL&fileSeq=1; swBizObjYn=N.",
      "hash": "sha256:8a05620526dbede55c19ce6e9cc0840c90fcd8e2edc2aa758243656f33526e50",
      "source_path": "backfill_hrcsp_ssstndrd_info/raw/getPublicPrcureThngInfoThng/2025-06/page_00001.json"
    }
  ]
}
