{
  "format": "g2b_opencrab_github_json_evidence_shard_v2_50_rows",
  "dataset": "g2b-public-procurement-9space-1500n-25mb-v1",
  "layout": "flat-root-json-50-rows-per-file",
  "shard_index": 115,
  "item_start_1based": 5701,
  "item_end_1based": 5750,
  "items_in_shard": 50,
  "total_items_all_shards": 10001,
  "items": [
    {
      "source_line": 5701,
      "chunk_id": "chunk:g2b:sentence:9908f028a7c0c6fead3afb6b",
      "evidence_id": "evidence:g2b:sentence:row:2bdd811ca79977038c2b5e0f",
      "document_id": "doc:g2b:source:671f1fe1fdab90d19e76841d",
      "service": "backfill_prdct_mng_info",
      "operation": "getPrdctClsfcNoUslfsvc",
      "source_file": "backfill_prdct_mng_info/raw/getPrdctClsfcNoUslfsvc/2024-02/page_00002.json",
      "text": "G2B public OpenAPI row. service=backfill_prdct_mng_info. operation=getPrdctClsfcNoUslfsvc. source_file=raw/getPrdctClsfcNoUslfsvc/2024-02/page_00002.json. row_index=31. prdctClsfcNo=23241402; prdctClsfcNoNm=평면연삭기; endDate=9999-12-31; rgstDate=2025-01-04; uslfsvc=13.",
      "hash": "sha256:4b0d7dfab27630ef7359f2a6a1af1f5741a841de64c029b890aa2a6671cda37a",
      "source_path": "backfill_prdct_mng_info/raw/getPrdctClsfcNoUslfsvc/2024-02/page_00002.json",
      "opencrab_probe_marker": "OPENCRAB_JSON_50_SHARD_115_FIRST_ROW_05701"
    },
    {
      "source_line": 5702,
      "chunk_id": "chunk:g2b:sentence:2371e2d7372253de6f7df429",
      "evidence_id": "evidence:g2b:sentence:row:a487077775ed02c4de2357a7",
      "document_id": "doc:g2b:source:671f1fe1fdab90d19e76841d",
      "service": "backfill_prdct_mng_info",
      "operation": "getPrdctClsfcNoUslfsvc",
      "source_file": "backfill_prdct_mng_info/raw/getPrdctClsfcNoUslfsvc/2024-02/page_00002.json",
      "text": "G2B public OpenAPI row. service=backfill_prdct_mng_info. operation=getPrdctClsfcNoUslfsvc. source_file=raw/getPrdctClsfcNoUslfsvc/2024-02/page_00002.json. row_index=32. prdctClsfcNo=23241407; prdctClsfcNoNm=원통연삭기; endDate=9999-12-31; rgstDate=2025-01-04; uslfsvc=13.",
      "hash": "sha256:a3530e8a7bdf09ed7cbc1619a58cb7d0347a5c38dbb660c8b6bff4729f736eeb",
      "source_path": "backfill_prdct_mng_info/raw/getPrdctClsfcNoUslfsvc/2024-02/page_00002.json"
    },
    {
      "source_line": 5703,
      "chunk_id": "chunk:g2b:sentence:c4eae4fce10d5f1046967647",
      "evidence_id": "evidence:g2b:sentence:row:f21f943e1cec1fedf4acbb47",
      "document_id": "doc:g2b:source:671f1fe1fdab90d19e76841d",
      "service": "backfill_prdct_mng_info",
      "operation": "getPrdctClsfcNoUslfsvc",
      "source_file": "backfill_prdct_mng_info/raw/getPrdctClsfcNoUslfsvc/2024-02/page_00002.json",
      "text": "G2B public OpenAPI row. service=backfill_prdct_mng_info. operation=getPrdctClsfcNoUslfsvc. source_file=raw/getPrdctClsfcNoUslfsvc/2024-02/page_00002.json. row_index=33. prdctClsfcNo=23241502; prdctClsfcNoNm=전해가공기; endDate=9999-12-31; rgstDate=2025-01-04; uslfsvc=11.",
      "hash": "sha256:162a69ac172b566be6eec37ecea0ee7643bf67926d6fc7c1c88e574e906d4dd7",
      "source_path": "backfill_prdct_mng_info/raw/getPrdctClsfcNoUslfsvc/2024-02/page_00002.json"
    },
    {
      "source_line": 5704,
      "chunk_id": "chunk:g2b:sentence:980977ad2f1a81a0cf348035",
      "evidence_id": "evidence:g2b:sentence:row:d9b489f91967c49329934993",
      "document_id": "doc:g2b:source:671f1fe1fdab90d19e76841d",
      "service": "backfill_prdct_mng_info",
      "operation": "getPrdctClsfcNoUslfsvc",
      "source_file": "backfill_prdct_mng_info/raw/getPrdctClsfcNoUslfsvc/2024-02/page_00002.json",
      "text": "G2B public OpenAPI row. service=backfill_prdct_mng_info. operation=getPrdctClsfcNoUslfsvc. source_file=raw/getPrdctClsfcNoUslfsvc/2024-02/page_00002.json. row_index=34. prdctClsfcNo=23241506; prdctClsfcNoNm=플라스마절단기; endDate=9999-12-31; rgstDate=2025-01-04; uslfsvc=12.",
      "hash": "sha256:9a08314367f373aada094d07e0da410cb1fb801133be1c80fd6ff6512637f826",
      "source_path": "backfill_prdct_mng_info/raw/getPrdctClsfcNoUslfsvc/2024-02/page_00002.json"
    },
    {
      "source_line": 5705,
      "chunk_id": "chunk:g2b:sentence:ed61b45ea8e528678f0b15cd",
      "evidence_id": "evidence:g2b:sentence:row:e46c0072ffc038ce49038e1c",
      "document_id": "doc:g2b:source:671f1fe1fdab90d19e76841d",
      "service": "backfill_prdct_mng_info",
      "operation": "getPrdctClsfcNoUslfsvc",
      "source_file": "backfill_prdct_mng_info/raw/getPrdctClsfcNoUslfsvc/2024-02/page_00002.json",
      "text": "G2B public OpenAPI row. service=backfill_prdct_mng_info. operation=getPrdctClsfcNoUslfsvc. source_file=raw/getPrdctClsfcNoUslfsvc/2024-02/page_00002.json. row_index=35. prdctClsfcNo=23241509; prdctClsfcNoNm=금속띠톱머신; endDate=9999-12-31; rgstDate=2025-01-04; uslfsvc=12.",
      "hash": "sha256:800dcebeeede8e912c9b034df34fb67855594a3d9691d6a072e1211242b87c80",
      "source_path": "backfill_prdct_mng_info/raw/getPrdctClsfcNoUslfsvc/2024-02/page_00002.json"
    },
    {
      "source_line": 5706,
      "chunk_id": "chunk:g2b:sentence:7369dd7955d6f997b2e613b0",
      "evidence_id": "evidence:g2b:sentence:row:67cd084e61bd2de5d6ddf959",
      "document_id": "doc:g2b:source:671f1fe1fdab90d19e76841d",
      "service": "backfill_prdct_mng_info",
      "operation": "getPrdctClsfcNoUslfsvc",
      "source_file": "backfill_prdct_mng_info/raw/getPrdctClsfcNoUslfsvc/2024-02/page_00002.json",
      "text": "G2B public OpenAPI row. service=backfill_prdct_mng_info. operation=getPrdctClsfcNoUslfsvc. source_file=raw/getPrdctClsfcNoUslfsvc/2024-02/page_00002.json. row_index=36. prdctClsfcNo=23241511; prdctClsfcNoNm=나사절삭기; endDate=9999-12-31; rgstDate=2025-01-04; uslfsvc=11.",
      "hash": "sha256:7528234a5dd51c3dcd7df006d4aa270bd85d29707b99f481d6e8786ce54d798d",
      "source_path": "backfill_prdct_mng_info/raw/getPrdctClsfcNoUslfsvc/2024-02/page_00002.json"
    },
    {
      "source_line": 5707,
      "chunk_id": "chunk:g2b:sentence:c1e65dffff3ff5da5a206a75",
      "evidence_id": "evidence:g2b:sentence:row:9b2193c7d88c580682acec61",
      "document_id": "doc:g2b:source:671f1fe1fdab90d19e76841d",
      "service": "backfill_prdct_mng_info",
      "operation": "getPrdctClsfcNoUslfsvc",
      "source_file": "backfill_prdct_mng_info/raw/getPrdctClsfcNoUslfsvc/2024-02/page_00002.json",
      "text": "G2B public OpenAPI row. service=backfill_prdct_mng_info. operation=getPrdctClsfcNoUslfsvc. source_file=raw/getPrdctClsfcNoUslfsvc/2024-02/page_00002.json. row_index=37. prdctClsfcNo=23241596; prdctClsfcNoNm=방전가공기기; endDate=9999-12-31; rgstDate=2025-01-04; uslfsvc=12.",
      "hash": "sha256:dee7946526ca3da1101ef1e9eb381b266ef1f8aeb4df80309fa45824a3ad6075",
      "source_path": "backfill_prdct_mng_info/raw/getPrdctClsfcNoUslfsvc/2024-02/page_00002.json"
    },
    {
      "source_line": 5708,
      "chunk_id": "chunk:g2b:sentence:4a7df609789337adf8c2cbd2",
      "evidence_id": "evidence:g2b:sentence:row:2a75fc215057b73adfa8f37f",
      "document_id": "doc:g2b:source:671f1fe1fdab90d19e76841d",
      "service": "backfill_prdct_mng_info",
      "operation": "getPrdctClsfcNoUslfsvc",
      "source_file": "backfill_prdct_mng_info/raw/getPrdctClsfcNoUslfsvc/2024-02/page_00002.json",
      "text": "G2B public OpenAPI row. service=backfill_prdct_mng_info. operation=getPrdctClsfcNoUslfsvc. source_file=raw/getPrdctClsfcNoUslfsvc/2024-02/page_00002.json. row_index=38. prdctClsfcNo=23241598; prdctClsfcNoNm=자동가스절단기; endDate=9999-12-31; rgstDate=2025-01-04; uslfsvc=10.",
      "hash": "sha256:e7499ff33d79ce6c05aa2c21a457c5a373e83969d1e4d2a9142a66594d97c297",
      "source_path": "backfill_prdct_mng_info/raw/getPrdctClsfcNoUslfsvc/2024-02/page_00002.json"
    },
    {
      "source_line": 5709,
      "chunk_id": "chunk:g2b:sentence:fdf2c030ff4643c78ed686df",
      "evidence_id": "evidence:g2b:sentence:row:d52eb181905ff81bb088ea12",
      "document_id": "doc:g2b:source:671f1fe1fdab90d19e76841d",
      "service": "backfill_prdct_mng_info",
      "operation": "getPrdctClsfcNoUslfsvc",
      "source_file": "backfill_prdct_mng_info/raw/getPrdctClsfcNoUslfsvc/2024-02/page_00002.json",
      "text": "G2B public OpenAPI row. service=backfill_prdct_mng_info. operation=getPrdctClsfcNoUslfsvc. source_file=raw/getPrdctClsfcNoUslfsvc/2024-02/page_00002.json. row_index=39. prdctClsfcNo=23241802; prdctClsfcNoNm=다축드릴링머신; endDate=9999-12-31; rgstDate=2025-01-04; uslfsvc=12.",
      "hash": "sha256:72998d9d55b6d3a1853d7589fb079dc9951022680c7eb5ded560a275557720ab",
      "source_path": "backfill_prdct_mng_info/raw/getPrdctClsfcNoUslfsvc/2024-02/page_00002.json"
    },
    {
      "source_line": 5710,
      "chunk_id": "chunk:g2b:sentence:7d5ae3f840b5549cfc6e55b1",
      "evidence_id": "evidence:g2b:sentence:row:dc599f7a9bf23a9b15a42876",
      "document_id": "doc:g2b:source:671f1fe1fdab90d19e76841d",
      "service": "backfill_prdct_mng_info",
      "operation": "getPrdctClsfcNoUslfsvc",
      "source_file": "backfill_prdct_mng_info/raw/getPrdctClsfcNoUslfsvc/2024-02/page_00002.json",
      "text": "G2B public OpenAPI row. service=backfill_prdct_mng_info. operation=getPrdctClsfcNoUslfsvc. source_file=raw/getPrdctClsfcNoUslfsvc/2024-02/page_00002.json. row_index=40. prdctClsfcNo=23241809; prdctClsfcNoNm=탁상드릴링머신; endDate=9999-12-31; rgstDate=2025-01-04; uslfsvc=11.",
      "hash": "sha256:b42bed8f9f70bc7e59949bbffa81d0b8b2f7d446d54c56ffeb62b8359b2494ac",
      "source_path": "backfill_prdct_mng_info/raw/getPrdctClsfcNoUslfsvc/2024-02/page_00002.json"
    },
    {
      "source_line": 5711,
      "chunk_id": "chunk:g2b:sentence:cd2cf18d09a670cba7dbbfbd",
      "evidence_id": "evidence:g2b:sentence:row:c4dcd8547dc2ca2cd1b3f0a8",
      "document_id": "doc:g2b:source:671f1fe1fdab90d19e76841d",
      "service": "backfill_prdct_mng_info",
      "operation": "getPrdctClsfcNoUslfsvc",
      "source_file": "backfill_prdct_mng_info/raw/getPrdctClsfcNoUslfsvc/2024-02/page_00002.json",
      "text": "G2B public OpenAPI row. service=backfill_prdct_mng_info. operation=getPrdctClsfcNoUslfsvc. source_file=raw/getPrdctClsfcNoUslfsvc/2024-02/page_00002.json. row_index=41. prdctClsfcNo=23241894; prdctClsfcNoNm=CNC드릴링머신; endDate=9999-12-31; rgstDate=2025-01-04; uslfsvc=12.",
      "hash": "sha256:2b5d33e34277f91fd9c8cb15595ba2e5ea4443955046e9cc7a56c1d4512ffe3f",
      "source_path": "backfill_prdct_mng_info/raw/getPrdctClsfcNoUslfsvc/2024-02/page_00002.json"
    },
    {
      "source_line": 5712,
      "chunk_id": "chunk:g2b:sentence:b2c60a7280080afb82abbd78",
      "evidence_id": "evidence:g2b:sentence:row:e58615fcca78c663ebe04680",
      "document_id": "doc:g2b:source:671f1fe1fdab90d19e76841d",
      "service": "backfill_prdct_mng_info",
      "operation": "getPrdctClsfcNoUslfsvc",
      "source_file": "backfill_prdct_mng_info/raw/getPrdctClsfcNoUslfsvc/2024-02/page_00002.json",
      "text": "G2B public OpenAPI row. service=backfill_prdct_mng_info. operation=getPrdctClsfcNoUslfsvc. source_file=raw/getPrdctClsfcNoUslfsvc/2024-02/page_00002.json. row_index=42. prdctClsfcNo=23241896; prdctClsfcNoNm=레이디얼드릴링머신; endDate=9999-12-31; rgstDate=2025-01-04; uslfsvc=12.",
      "hash": "sha256:8f48f1a91b2799de165483763ee91204a7bd40c94300b05ef62dfb803dbe2f36",
      "source_path": "backfill_prdct_mng_info/raw/getPrdctClsfcNoUslfsvc/2024-02/page_00002.json"
    },
    {
      "source_line": 5713,
      "chunk_id": "chunk:g2b:sentence:39b338f08e6599ca49b807db",
      "evidence_id": "evidence:g2b:sentence:row:657ecff427cf0576104e87c8",
      "document_id": "doc:g2b:source:671f1fe1fdab90d19e76841d",
      "service": "backfill_prdct_mng_info",
      "operation": "getPrdctClsfcNoUslfsvc",
      "source_file": "backfill_prdct_mng_info/raw/getPrdctClsfcNoUslfsvc/2024-02/page_00002.json",
      "text": "G2B public OpenAPI row. service=backfill_prdct_mng_info. operation=getPrdctClsfcNoUslfsvc. source_file=raw/getPrdctClsfcNoUslfsvc/2024-02/page_00002.json. row_index=43. prdctClsfcNo=23241898; prdctClsfcNoNm=직립드릴링머신; endDate=9999-12-31; rgstDate=2025-01-04; uslfsvc=12.",
      "hash": "sha256:4e994708466f0ae78a2d201ccc2211b14defd77580241228a3faf3ee34e19b85",
      "source_path": "backfill_prdct_mng_info/raw/getPrdctClsfcNoUslfsvc/2024-02/page_00002.json"
    },
    {
      "source_line": 5714,
      "chunk_id": "chunk:g2b:sentence:dd5e672fc5a5b205c4924de1",
      "evidence_id": "evidence:g2b:sentence:row:1869905d938994521b9fd005",
      "document_id": "doc:g2b:source:671f1fe1fdab90d19e76841d",
      "service": "backfill_prdct_mng_info",
      "operation": "getPrdctClsfcNoUslfsvc",
      "source_file": "backfill_prdct_mng_info/raw/getPrdctClsfcNoUslfsvc/2024-02/page_00002.json",
      "text": "G2B public OpenAPI row. service=backfill_prdct_mng_info. operation=getPrdctClsfcNoUslfsvc. source_file=raw/getPrdctClsfcNoUslfsvc/2024-02/page_00002.json. row_index=44. prdctClsfcNo=23242305; prdctClsfcNoNm=터릿선반; endDate=9999-12-31; rgstDate=2025-01-04; uslfsvc=12.",
      "hash": "sha256:33b7a4f02252ed2c5540e104e4a644556b96546014027de67beba765173bab63",
      "source_path": "backfill_prdct_mng_info/raw/getPrdctClsfcNoUslfsvc/2024-02/page_00002.json"
    },
    {
      "source_line": 5715,
      "chunk_id": "chunk:g2b:sentence:dd63a5d47b5b02364350e429",
      "evidence_id": "evidence:g2b:sentence:row:957f9458f11158eee1d539f6",
      "document_id": "doc:g2b:source:671f1fe1fdab90d19e76841d",
      "service": "backfill_prdct_mng_info",
      "operation": "getPrdctClsfcNoUslfsvc",
      "source_file": "backfill_prdct_mng_info/raw/getPrdctClsfcNoUslfsvc/2024-02/page_00002.json",
      "text": "G2B public OpenAPI row. service=backfill_prdct_mng_info. operation=getPrdctClsfcNoUslfsvc. source_file=raw/getPrdctClsfcNoUslfsvc/2024-02/page_00002.json. row_index=45. prdctClsfcNo=23242398; prdctClsfcNoNm=선반; endDate=9999-12-31; rgstDate=2025-01-04; uslfsvc=13.",
      "hash": "sha256:40d53ada09846927946dc333e8445c44d9703d73868ad63605b94c4a94cab026",
      "source_path": "backfill_prdct_mng_info/raw/getPrdctClsfcNoUslfsvc/2024-02/page_00002.json"
    },
    {
      "source_line": 5716,
      "chunk_id": "chunk:g2b:sentence:8bc6571c68cc481ca8917a2b",
      "evidence_id": "evidence:g2b:sentence:row:bac56add08572667795a0384",
      "document_id": "doc:g2b:source:671f1fe1fdab90d19e76841d",
      "service": "backfill_prdct_mng_info",
      "operation": "getPrdctClsfcNoUslfsvc",
      "source_file": "backfill_prdct_mng_info/raw/getPrdctClsfcNoUslfsvc/2024-02/page_00002.json",
      "text": "G2B public OpenAPI row. service=backfill_prdct_mng_info. operation=getPrdctClsfcNoUslfsvc. source_file=raw/getPrdctClsfcNoUslfsvc/2024-02/page_00002.json. row_index=46. prdctClsfcNo=23242403; prdctClsfcNoNm=수직형머시닝센터; endDate=9999-12-31; rgstDate=2025-01-04; uslfsvc=12.",
      "hash": "sha256:13f2798b870ffecc368b15aaebea403dee5369485c96eaa129378a1e4662d22c",
      "source_path": "backfill_prdct_mng_info/raw/getPrdctClsfcNoUslfsvc/2024-02/page_00002.json"
    },
    {
      "source_line": 5717,
      "chunk_id": "chunk:g2b:sentence:520fdc8606c93f7e811a5576",
      "evidence_id": "evidence:g2b:sentence:row:f3f5b33a7aa6ac88097b7304",
      "document_id": "doc:g2b:source:671f1fe1fdab90d19e76841d",
      "service": "backfill_prdct_mng_info",
      "operation": "getPrdctClsfcNoUslfsvc",
      "source_file": "backfill_prdct_mng_info/raw/getPrdctClsfcNoUslfsvc/2024-02/page_00002.json",
      "text": "G2B public OpenAPI row. service=backfill_prdct_mng_info. operation=getPrdctClsfcNoUslfsvc. source_file=raw/getPrdctClsfcNoUslfsvc/2024-02/page_00002.json. row_index=47. prdctClsfcNo=23242501; prdctClsfcNoNm=베드형밀링머신; endDate=9999-12-31; rgstDate=2025-01-04; uslfsvc=10.",
      "hash": "sha256:c5872b81e7192a04da0610f141017ba472d1ba653e06b2d0b30c063afecda463",
      "source_path": "backfill_prdct_mng_info/raw/getPrdctClsfcNoUslfsvc/2024-02/page_00002.json"
    },
    {
      "source_line": 5718,
      "chunk_id": "chunk:g2b:sentence:b833f8cee057d6c71c172fd1",
      "evidence_id": "evidence:g2b:sentence:row:3a77f9af063a57103fd93f15",
      "document_id": "doc:g2b:source:671f1fe1fdab90d19e76841d",
      "service": "backfill_prdct_mng_info",
      "operation": "getPrdctClsfcNoUslfsvc",
      "source_file": "backfill_prdct_mng_info/raw/getPrdctClsfcNoUslfsvc/2024-02/page_00002.json",
      "text": "G2B public OpenAPI row. service=backfill_prdct_mng_info. operation=getPrdctClsfcNoUslfsvc. source_file=raw/getPrdctClsfcNoUslfsvc/2024-02/page_00002.json. row_index=48. prdctClsfcNo=23242507; prdctClsfcNoNm=만능밀링머신; endDate=9999-12-31; rgstDate=2025-01-04; uslfsvc=12.",
      "hash": "sha256:75a3e90f2e24284ca3573dfad036e7b1b9e8d009c70831d4175c0025ef9aef99",
      "source_path": "backfill_prdct_mng_info/raw/getPrdctClsfcNoUslfsvc/2024-02/page_00002.json"
    },
    {
      "source_line": 5719,
      "chunk_id": "chunk:g2b:sentence:4fcf06d04d3fc14605e3e6b0",
      "evidence_id": "evidence:g2b:sentence:row:fc8a9f7515b5521b50375af3",
      "document_id": "doc:g2b:source:671f1fe1fdab90d19e76841d",
      "service": "backfill_prdct_mng_info",
      "operation": "getPrdctClsfcNoUslfsvc",
      "source_file": "backfill_prdct_mng_info/raw/getPrdctClsfcNoUslfsvc/2024-02/page_00002.json",
      "text": "G2B public OpenAPI row. service=backfill_prdct_mng_info. operation=getPrdctClsfcNoUslfsvc. source_file=raw/getPrdctClsfcNoUslfsvc/2024-02/page_00002.json. row_index=49. prdctClsfcNo=23242509; prdctClsfcNoNm=터릿밀링머신; endDate=9999-12-31; rgstDate=2025-01-04; uslfsvc=10.",
      "hash": "sha256:5d90efb7331ca93cfe46ede3445e8939166ae2c05a770da3a1664cbd49bd2fba",
      "source_path": "backfill_prdct_mng_info/raw/getPrdctClsfcNoUslfsvc/2024-02/page_00002.json"
    },
    {
      "source_line": 5720,
      "chunk_id": "chunk:g2b:sentence:9f73507c2287f10b39e9adf1",
      "evidence_id": "evidence:g2b:sentence:row:aef35f157a4c0295452ace7a",
      "document_id": "doc:g2b:source:ef1b5d8a73bbeb6fd7080c7e",
      "service": "backfill_price_info",
      "operation": "getPriceInfoListFcltyCmmnMtrilBildng",
      "source_file": "backfill_price_info/raw/getPriceInfoListFcltyCmmnMtrilBildng/2026-05/page_00001.json",
      "text": "G2B public OpenAPI row. service=backfill_price_info. operation=getPriceInfoListFcltyCmmnMtrilBildng. source_file=raw/getPriceInfoListFcltyCmmnMtrilBildng/2026-05/page_00001.json. row_index=0. invstDeptTelNo=042-724-7109; invstOfclNm=이상대; prdctClsfcNo=11122001; prdctClsfcNoNm=보통합판; prdctIdntNo=20142422; splyJrsdctRgnNm=002; bsnsDivCd=포110002; bsnsDivNm=시설공통자재(건축); distbStep=수요자지정장소도; dlvryCndtnNm=현장도착도; invstDeptNm=건축설비과; krnPrdctNm=보통합판, 1급, 18×1220×2440mm; nticeDt=2024-10-30 16:58:14; prce=51954; prceDiv=기타가격; prceNticeNo=R24CW21466456; unit=매; vatYnNm=부가가치세별도.",
      "hash": "sha256:1c1a5b3f2f3d97889b348f7ccc9a7cd2020a192e1aab14c1d4f7d2719a5d445c",
      "source_path": "backfill_price_info/raw/getPriceInfoListFcltyCmmnMtrilBildng/2026-05/page_00001.json"
    },
    {
      "source_line": 5721,
      "chunk_id": "chunk:g2b:sentence:598369c21ac0b0962bd108d3",
      "evidence_id": "evidence:g2b:sentence:row:57026e29cca48a32195abb29",
      "document_id": "doc:g2b:source:ef1b5d8a73bbeb6fd7080c7e",
      "service": "backfill_price_info",
      "operation": "getPriceInfoListFcltyCmmnMtrilBildng",
      "source_file": "backfill_price_info/raw/getPriceInfoListFcltyCmmnMtrilBildng/2026-05/page_00001.json",
      "text": "G2B public OpenAPI row. service=backfill_price_info. operation=getPriceInfoListFcltyCmmnMtrilBildng. source_file=raw/getPriceInfoListFcltyCmmnMtrilBildng/2026-05/page_00001.json. row_index=1. invstDeptTelNo=042-724-7109; invstOfclNm=이상대; prdctClsfcNo=11122001; prdctClsfcNoNm=내수합판; prdctIdntNo=20142457; splyJrsdctRgnNm=002; bsnsDivCd=포110002; bsnsDivNm=시설공통자재(건축); distbStep=수요자지정장소도; dlvryCndtnNm=현장도착도; invstDeptNm=건축설비과; krnPrdctNm=내수합판, 1급, 18×910×1820mm; nticeDt=2024-10-30 16:58:14; prce=30989; prceDiv=기타가격; prceNticeNo=R24CW21466056; unit=매; vatYnNm=부가가치세별도.",
      "hash": "sha256:247a0ae61d8cdbe90a3a46fce3fde1efd2cacc2909444d468d7cb120a999d2ae",
      "source_path": "backfill_price_info/raw/getPriceInfoListFcltyCmmnMtrilBildng/2026-05/page_00001.json"
    },
    {
      "source_line": 5722,
      "chunk_id": "chunk:g2b:sentence:de8b992325689b17b72dfb60",
      "evidence_id": "evidence:g2b:sentence:row:648c23e84d35e456f8b9a670",
      "document_id": "doc:g2b:source:ef1b5d8a73bbeb6fd7080c7e",
      "service": "backfill_price_info",
      "operation": "getPriceInfoListFcltyCmmnMtrilBildng",
      "source_file": "backfill_price_info/raw/getPriceInfoListFcltyCmmnMtrilBildng/2026-05/page_00001.json",
      "text": "G2B public OpenAPI row. service=backfill_price_info. operation=getPriceInfoListFcltyCmmnMtrilBildng. source_file=raw/getPriceInfoListFcltyCmmnMtrilBildng/2026-05/page_00001.json. row_index=2. invstDeptTelNo=042-724-7109; invstOfclNm=이상대; prdctClsfcNo=11122001; prdctClsfcNoNm=내수합판; prdctIdntNo=20142462; splyJrsdctRgnNm=002; bsnsDivCd=포110002; bsnsDivNm=시설공통자재(건축); distbStep=수요자지정장소도; dlvryCndtnNm=현장도착도; invstDeptNm=건축설비과; krnPrdctNm=내수합판, 1급, 18×1220×2440mm; nticeDt=2024-10-30 16:58:14; prce=17887; prceDiv=기타가격; prceNticeNo=R24CW21466066; unit=㎡; vatYnNm=부가가치세별도.",
      "hash": "sha256:6e4b743c9160d425077b1d3f963faef57bb3c47c0f092a7d7bbef547aa87754f",
      "source_path": "backfill_price_info/raw/getPriceInfoListFcltyCmmnMtrilBildng/2026-05/page_00001.json"
    },
    {
      "source_line": 5723,
      "chunk_id": "chunk:g2b:sentence:01b4a5bb036ab47620372b07",
      "evidence_id": "evidence:g2b:sentence:row:bad763be9a362b72f2b8c4f6",
      "document_id": "doc:g2b:source:ef1b5d8a73bbeb6fd7080c7e",
      "service": "backfill_price_info",
      "operation": "getPriceInfoListFcltyCmmnMtrilBildng",
      "source_file": "backfill_price_info/raw/getPriceInfoListFcltyCmmnMtrilBildng/2026-05/page_00001.json",
      "text": "G2B public OpenAPI row. service=backfill_price_info. operation=getPriceInfoListFcltyCmmnMtrilBildng. source_file=raw/getPriceInfoListFcltyCmmnMtrilBildng/2026-05/page_00001.json. row_index=3. invstDeptTelNo=042-724-7109; invstOfclNm=이상대; prdctClsfcNo=11122001; prdctClsfcNoNm=내수합판; prdctIdntNo=20142452; splyJrsdctRgnNm=002; bsnsDivCd=포110002; bsnsDivNm=시설공통자재(건축); distbStep=수요자지정장소도; dlvryCndtnNm=현장도착도; invstDeptNm=건축설비과; krnPrdctNm=내수합판, 1급, 12×910×1820mm; nticeDt=2024-10-30 16:58:14; prce=12114; prceDiv=기타가격; prceNticeNo=R24CW21466046; unit=㎡; vatYnNm=부가가치세별도.",
      "hash": "sha256:497774c9422a1da491f220fd6df592edb91861d46e9cd94effeb0d2746b3f46e",
      "source_path": "backfill_price_info/raw/getPriceInfoListFcltyCmmnMtrilBildng/2026-05/page_00001.json"
    },
    {
      "source_line": 5724,
      "chunk_id": "chunk:g2b:sentence:740a9fe46650905b21807210",
      "evidence_id": "evidence:g2b:sentence:row:7665d7b1ddf6a1aa79955c17",
      "document_id": "doc:g2b:source:ef1b5d8a73bbeb6fd7080c7e",
      "service": "backfill_price_info",
      "operation": "getPriceInfoListFcltyCmmnMtrilBildng",
      "source_file": "backfill_price_info/raw/getPriceInfoListFcltyCmmnMtrilBildng/2026-05/page_00001.json",
      "text": "G2B public OpenAPI row. service=backfill_price_info. operation=getPriceInfoListFcltyCmmnMtrilBildng. source_file=raw/getPriceInfoListFcltyCmmnMtrilBildng/2026-05/page_00001.json. row_index=4. invstDeptTelNo=042-724-7109; invstOfclNm=이상대; prdctClsfcNo=11122001; prdctClsfcNoNm=내수합판; prdctIdntNo=20142463; splyJrsdctRgnNm=002; bsnsDivCd=포110002; bsnsDivNm=시설공통자재(건축); distbStep=수요자지정장소도; dlvryCndtnNm=현장도착도; invstDeptNm=건축설비과; krnPrdctNm=내수합판, 1급, 18×1220×2440mm; nticeDt=2024-10-30 16:58:14; prce=53248; prceDiv=기타가격; prceNticeNo=R24CW21466068; unit=매; vatYnNm=부가가치세별도.",
      "hash": "sha256:143a2f549a0c88a114aff99f09c0ac741019c44c309a27d2c8708048f246ca7b",
      "source_path": "backfill_price_info/raw/getPriceInfoListFcltyCmmnMtrilBildng/2026-05/page_00001.json"
    },
    {
      "source_line": 5725,
      "chunk_id": "chunk:g2b:sentence:88c8f773d85e88bef2b72a23",
      "evidence_id": "evidence:g2b:sentence:row:8a9e19a6602d9e5e02cd608a",
      "document_id": "doc:g2b:source:ef1b5d8a73bbeb6fd7080c7e",
      "service": "backfill_price_info",
      "operation": "getPriceInfoListFcltyCmmnMtrilBildng",
      "source_file": "backfill_price_info/raw/getPriceInfoListFcltyCmmnMtrilBildng/2026-05/page_00001.json",
      "text": "G2B public OpenAPI row. service=backfill_price_info. operation=getPriceInfoListFcltyCmmnMtrilBildng. source_file=raw/getPriceInfoListFcltyCmmnMtrilBildng/2026-05/page_00001.json. row_index=5. invstDeptTelNo=042-724-7109; invstOfclNm=이상대; prdctClsfcNo=11122001; prdctClsfcNoNm=내수합판; prdctIdntNo=20142460; splyJrsdctRgnNm=002; bsnsDivCd=포110002; bsnsDivNm=시설공통자재(건축); distbStep=수요자지정장소도; dlvryCndtnNm=현장도착도; invstDeptNm=건축설비과; krnPrdctNm=내수합판, 1급, 15×1220×2440mm; nticeDt=2024-10-30 16:58:14; prce=14828; prceDiv=기타가격; prceNticeNo=R24CW21466062; unit=㎡; vatYnNm=부가가치세별도.",
      "hash": "sha256:889667813639336b28291669d22fa8bd6dfd6514410df3f7247ef3342a3674e3",
      "source_path": "backfill_price_info/raw/getPriceInfoListFcltyCmmnMtrilBildng/2026-05/page_00001.json"
    },
    {
      "source_line": 5726,
      "chunk_id": "chunk:g2b:sentence:9e958e266cfef73f7c963d15",
      "evidence_id": "evidence:g2b:sentence:row:aa35238870876f4a1dbebad0",
      "document_id": "doc:g2b:source:ef1b5d8a73bbeb6fd7080c7e",
      "service": "backfill_price_info",
      "operation": "getPriceInfoListFcltyCmmnMtrilBildng",
      "source_file": "backfill_price_info/raw/getPriceInfoListFcltyCmmnMtrilBildng/2026-05/page_00001.json",
      "text": "G2B public OpenAPI row. service=backfill_price_info. operation=getPriceInfoListFcltyCmmnMtrilBildng. source_file=raw/getPriceInfoListFcltyCmmnMtrilBildng/2026-05/page_00001.json. row_index=6. invstDeptTelNo=042-724-7109; invstOfclNm=이상대; prdctClsfcNo=11122001; prdctClsfcNoNm=내수합판; prdctIdntNo=20142454; splyJrsdctRgnNm=002; bsnsDivCd=포110002; bsnsDivNm=시설공통자재(건축); distbStep=수요자지정장소도; dlvryCndtnNm=현장도착도; invstDeptNm=건축설비과; krnPrdctNm=내수합판, 1급, 15×910×1820mm; nticeDt=2024-10-30 16:58:14; prce=16826; prceDiv=기타가격; prceNticeNo=R24CW21466050; unit=㎡; vatYnNm=부가가치세별도.",
      "hash": "sha256:fd4e8ea505486258891c1e4109ca457b51b0bd9d7699c07d31ddd04be0184574",
      "source_path": "backfill_price_info/raw/getPriceInfoListFcltyCmmnMtrilBildng/2026-05/page_00001.json"
    },
    {
      "source_line": 5727,
      "chunk_id": "chunk:g2b:sentence:a1d3f2fb4c362b3d5b067077",
      "evidence_id": "evidence:g2b:sentence:row:85145b1d57903f18e225ee77",
      "document_id": "doc:g2b:source:ef1b5d8a73bbeb6fd7080c7e",
      "service": "backfill_price_info",
      "operation": "getPriceInfoListFcltyCmmnMtrilBildng",
      "source_file": "backfill_price_info/raw/getPriceInfoListFcltyCmmnMtrilBildng/2026-05/page_00001.json",
      "text": "G2B public OpenAPI row. service=backfill_price_info. operation=getPriceInfoListFcltyCmmnMtrilBildng. source_file=raw/getPriceInfoListFcltyCmmnMtrilBildng/2026-05/page_00001.json. row_index=7. invstDeptTelNo=042-724-7109; invstOfclNm=이상대; prdctClsfcNo=11122001; prdctClsfcNoNm=내수합판; prdctIdntNo=20142455; splyJrsdctRgnNm=002; bsnsDivCd=포110002; bsnsDivNm=시설공통자재(건축); distbStep=수요자지정장소도; dlvryCndtnNm=현장도착도; invstDeptNm=건축설비과; krnPrdctNm=내수합판, 1급, 15×910×1820mm; nticeDt=2024-10-30 16:58:14; prce=27868; prceDiv=기타가격; prceNticeNo=R24CW21466052; unit=매; vatYnNm=부가가치세별도.",
      "hash": "sha256:dd5dff59b9593fa1e5eafbc59e7764adb3f304bde74577661e412d5f49c68aef",
      "source_path": "backfill_price_info/raw/getPriceInfoListFcltyCmmnMtrilBildng/2026-05/page_00001.json"
    },
    {
      "source_line": 5728,
      "chunk_id": "chunk:g2b:sentence:d153c40e5540d31e5a5f8fa4",
      "evidence_id": "evidence:g2b:sentence:row:73168c24bf2321091b3d84d2",
      "document_id": "doc:g2b:source:ef1b5d8a73bbeb6fd7080c7e",
      "service": "backfill_price_info",
      "operation": "getPriceInfoListFcltyCmmnMtrilBildng",
      "source_file": "backfill_price_info/raw/getPriceInfoListFcltyCmmnMtrilBildng/2026-05/page_00001.json",
      "text": "G2B public OpenAPI row. service=backfill_price_info. operation=getPriceInfoListFcltyCmmnMtrilBildng. source_file=raw/getPriceInfoListFcltyCmmnMtrilBildng/2026-05/page_00001.json. row_index=8. invstDeptTelNo=042-724-7109; invstOfclNm=이상대; prdctClsfcNo=11122001; prdctClsfcNoNm=내수합판; prdctIdntNo=20142459; splyJrsdctRgnNm=002; bsnsDivCd=포110002; bsnsDivNm=시설공통자재(건축); distbStep=수요자지정장소도; dlvryCndtnNm=현장도착도; invstDeptNm=건축설비과; krnPrdctNm=내수합판, 1급, 12×1220×2440mm; nticeDt=2024-10-30 16:58:14; prce=32550; prceDiv=기타가격; prceNticeNo=R24CW21466060; unit=매; vatYnNm=부가가치세별도.",
      "hash": "sha256:d34de4c617696a0a03d8850fea202a68e9513683d74b22ea2d7a4c2ab138814c",
      "source_path": "backfill_price_info/raw/getPriceInfoListFcltyCmmnMtrilBildng/2026-05/page_00001.json"
    },
    {
      "source_line": 5729,
      "chunk_id": "chunk:g2b:sentence:4ada8105541d65c8deb0c5b5",
      "evidence_id": "evidence:g2b:sentence:row:a280c70b18a4ec3ad864166f",
      "document_id": "doc:g2b:source:ef1b5d8a73bbeb6fd7080c7e",
      "service": "backfill_price_info",
      "operation": "getPriceInfoListFcltyCmmnMtrilBildng",
      "source_file": "backfill_price_info/raw/getPriceInfoListFcltyCmmnMtrilBildng/2026-05/page_00001.json",
      "text": "G2B public OpenAPI row. service=backfill_price_info. operation=getPriceInfoListFcltyCmmnMtrilBildng. source_file=raw/getPriceInfoListFcltyCmmnMtrilBildng/2026-05/page_00001.json. row_index=9. invstDeptTelNo=042-724-7109; invstOfclNm=이상대; prdctClsfcNo=11122001; prdctClsfcNoNm=내수합판; prdctIdntNo=20142453; splyJrsdctRgnNm=002; bsnsDivCd=포110002; bsnsDivNm=시설공통자재(건축); distbStep=수요자지정장소도; dlvryCndtnNm=현장도착도; invstDeptNm=건축설비과; krnPrdctNm=내수합판, 1급, 12×910×1820mm; nticeDt=2024-10-30 16:58:14; prce=20065; prceDiv=기타가격; prceNticeNo=R24CW21466048; unit=매; vatYnNm=부가가치세별도.",
      "hash": "sha256:5f5c85de5d7b9a780a63fa07720b267e39104f4449477ba0b235ca2c527fc60f",
      "source_path": "backfill_price_info/raw/getPriceInfoListFcltyCmmnMtrilBildng/2026-05/page_00001.json"
    },
    {
      "source_line": 5730,
      "chunk_id": "chunk:g2b:sentence:dd3fff2e802a300ab140e826",
      "evidence_id": "evidence:g2b:sentence:row:86608af0d8c8518ea7b14e5d",
      "document_id": "doc:g2b:source:ef1b5d8a73bbeb6fd7080c7e",
      "service": "backfill_price_info",
      "operation": "getPriceInfoListFcltyCmmnMtrilBildng",
      "source_file": "backfill_price_info/raw/getPriceInfoListFcltyCmmnMtrilBildng/2026-05/page_00001.json",
      "text": "G2B public OpenAPI row. service=backfill_price_info. operation=getPriceInfoListFcltyCmmnMtrilBildng. source_file=raw/getPriceInfoListFcltyCmmnMtrilBildng/2026-05/page_00001.json. row_index=10. invstDeptTelNo=042-724-7109; invstOfclNm=이상대; prdctClsfcNo=11122001; prdctClsfcNoNm=내수합판; prdctIdntNo=20142458; splyJrsdctRgnNm=002; bsnsDivCd=포110002; bsnsDivNm=시설공통자재(건축); distbStep=수요자지정장소도; dlvryCndtnNm=현장도착도; invstDeptNm=건축설비과; krnPrdctNm=내수합판, 1급, 12×1220×2440mm; nticeDt=2024-10-30 16:58:14; prce=10934; prceDiv=기타가격; prceNticeNo=R24CW21466058; unit=㎡; vatYnNm=부가가치세별도.",
      "hash": "sha256:edf259829ec1b0a30f7a1c2c323186a1c08603fc4f1578413093aa1117b84758",
      "source_path": "backfill_price_info/raw/getPriceInfoListFcltyCmmnMtrilBildng/2026-05/page_00001.json"
    },
    {
      "source_line": 5731,
      "chunk_id": "chunk:g2b:sentence:4b0102f4c2614d4d2045bb14",
      "evidence_id": "evidence:g2b:sentence:row:fecc35f7fa0b46520ffa13a9",
      "document_id": "doc:g2b:source:ef1b5d8a73bbeb6fd7080c7e",
      "service": "backfill_price_info",
      "operation": "getPriceInfoListFcltyCmmnMtrilBildng",
      "source_file": "backfill_price_info/raw/getPriceInfoListFcltyCmmnMtrilBildng/2026-05/page_00001.json",
      "text": "G2B public OpenAPI row. service=backfill_price_info. operation=getPriceInfoListFcltyCmmnMtrilBildng. source_file=raw/getPriceInfoListFcltyCmmnMtrilBildng/2026-05/page_00001.json. row_index=11. invstDeptTelNo=042-724-7109; invstOfclNm=이상대; prdctClsfcNo=11122001; prdctClsfcNoNm=내수합판; prdctIdntNo=20142461; splyJrsdctRgnNm=002; bsnsDivCd=포110002; bsnsDivNm=시설공통자재(건축); distbStep=수요자지정장소도; dlvryCndtnNm=현장도착도; invstDeptNm=건축설비과; krnPrdctNm=내수합판, 1급, 15×1220×2440mm; nticeDt=2024-10-30 16:58:14; prce=44143; prceDiv=기타가격; prceNticeNo=R24CW21466064; unit=매; vatYnNm=부가가치세별도.",
      "hash": "sha256:daa48bb41defaa265d19fa3e99a2001151385cafc53e2eea4a1280cdd7961a1c",
      "source_path": "backfill_price_info/raw/getPriceInfoListFcltyCmmnMtrilBildng/2026-05/page_00001.json"
    },
    {
      "source_line": 5732,
      "chunk_id": "chunk:g2b:sentence:b6a9b8a788ebd2fe01d0400f",
      "evidence_id": "evidence:g2b:sentence:row:d6287684d9e8dc0fa21cf2a2",
      "document_id": "doc:g2b:source:ef1b5d8a73bbeb6fd7080c7e",
      "service": "backfill_price_info",
      "operation": "getPriceInfoListFcltyCmmnMtrilBildng",
      "source_file": "backfill_price_info/raw/getPriceInfoListFcltyCmmnMtrilBildng/2026-05/page_00001.json",
      "text": "G2B public OpenAPI row. service=backfill_price_info. operation=getPriceInfoListFcltyCmmnMtrilBildng. source_file=raw/getPriceInfoListFcltyCmmnMtrilBildng/2026-05/page_00001.json. row_index=12. invstDeptTelNo=042-724-7109; invstOfclNm=이상대; prdctClsfcNo=11122001; prdctClsfcNoNm=내수합판; prdctIdntNo=20142456; splyJrsdctRgnNm=002; bsnsDivCd=포110002; bsnsDivNm=시설공통자재(건축); distbStep=수요자지정장소도; dlvryCndtnNm=현장도착도; invstDeptNm=건축설비과; krnPrdctNm=내수합판, 1급, 18×910×1820mm; nticeDt=2024-10-30 16:58:14; prce=18711; prceDiv=기타가격; prceNticeNo=R24CW21466054; unit=㎡; vatYnNm=부가가치세별도.",
      "hash": "sha256:3fc9801d1cb966c9eb444ee919ecf07e5824be06b2bc82a12270bbd7a5da48ad",
      "source_path": "backfill_price_info/raw/getPriceInfoListFcltyCmmnMtrilBildng/2026-05/page_00001.json"
    },
    {
      "source_line": 5733,
      "chunk_id": "chunk:g2b:sentence:8926fe2840d34f3342c64979",
      "evidence_id": "evidence:g2b:sentence:row:d0466df088869081053e8f70",
      "document_id": "doc:g2b:source:ef1b5d8a73bbeb6fd7080c7e",
      "service": "backfill_price_info",
      "operation": "getPriceInfoListFcltyCmmnMtrilBildng",
      "source_file": "backfill_price_info/raw/getPriceInfoListFcltyCmmnMtrilBildng/2026-05/page_00001.json",
      "text": "G2B public OpenAPI row. service=backfill_price_info. operation=getPriceInfoListFcltyCmmnMtrilBildng. source_file=raw/getPriceInfoListFcltyCmmnMtrilBildng/2026-05/page_00001.json. row_index=13. invstDeptTelNo=042-724-7109; invstOfclNm=이상대; prdctClsfcNo=11122001; prdctClsfcNoNm=보통합판; prdctIdntNo=20142417; splyJrsdctRgnNm=002; bsnsDivCd=포110002; bsnsDivNm=시설공통자재(건축); distbStep=수요자지정장소도; dlvryCndtnNm=현장도착도; invstDeptNm=건축설비과; krnPrdctNm=보통합판, 1급, 12×1220×2440mm; nticeDt=2024-10-30 16:58:14; prce=10373; prceDiv=기타가격; prceNticeNo=R24CW21466446; unit=㎡; vatYnNm=부가가치세별도.",
      "hash": "sha256:0bba3d9210313aaad671796891b3844e1dc87eab8cef9f4d66fc825ba5d5e329",
      "source_path": "backfill_price_info/raw/getPriceInfoListFcltyCmmnMtrilBildng/2026-05/page_00001.json"
    },
    {
      "source_line": 5734,
      "chunk_id": "chunk:g2b:sentence:05c940830c8f4895acdbaf8f",
      "evidence_id": "evidence:g2b:sentence:row:74b431cae21eeba8fae00a69",
      "document_id": "doc:g2b:source:ef1b5d8a73bbeb6fd7080c7e",
      "service": "backfill_price_info",
      "operation": "getPriceInfoListFcltyCmmnMtrilBildng",
      "source_file": "backfill_price_info/raw/getPriceInfoListFcltyCmmnMtrilBildng/2026-05/page_00001.json",
      "text": "G2B public OpenAPI row. service=backfill_price_info. operation=getPriceInfoListFcltyCmmnMtrilBildng. source_file=raw/getPriceInfoListFcltyCmmnMtrilBildng/2026-05/page_00001.json. row_index=14. invstDeptTelNo=042-724-7109; invstOfclNm=이상대; prdctClsfcNo=11122001; prdctClsfcNoNm=보통합판; prdctIdntNo=20935461; splyJrsdctRgnNm=002; bsnsDivCd=포110002; bsnsDivNm=시설공통자재(건축); distbStep=수요자지정장소도; dlvryCndtnNm=현장도착도; invstDeptNm=건축설비과; krnPrdctNm=보통합판, 보통합판, 1급, 3.6mm; nticeDt=2024-10-30 16:58:14; prce=4045; prceDiv=기타가격; prceNticeNo=R24CW21466430; unit=㎡; vatYnNm=부가가치세별도.",
      "hash": "sha256:54d87e58f7d4e958c60a1b45914d8776aa7465617ef6c2f9536e03450fb0a871",
      "source_path": "backfill_price_info/raw/getPriceInfoListFcltyCmmnMtrilBildng/2026-05/page_00001.json"
    },
    {
      "source_line": 5735,
      "chunk_id": "chunk:g2b:sentence:e2dbe22dbab935f5fe91ed49",
      "evidence_id": "evidence:g2b:sentence:row:636b8032921ea4c6d142184a",
      "document_id": "doc:g2b:source:ef1b5d8a73bbeb6fd7080c7e",
      "service": "backfill_price_info",
      "operation": "getPriceInfoListFcltyCmmnMtrilBildng",
      "source_file": "backfill_price_info/raw/getPriceInfoListFcltyCmmnMtrilBildng/2026-05/page_00001.json",
      "text": "G2B public OpenAPI row. service=backfill_price_info. operation=getPriceInfoListFcltyCmmnMtrilBildng. source_file=raw/getPriceInfoListFcltyCmmnMtrilBildng/2026-05/page_00001.json. row_index=15. invstDeptTelNo=042-724-7109; invstOfclNm=이상대; prdctClsfcNo=11122001; prdctClsfcNoNm=보통합판; prdctIdntNo=20142421; splyJrsdctRgnNm=002; bsnsDivCd=포110002; bsnsDivNm=시설공통자재(건축); distbStep=수요자지정장소도; dlvryCndtnNm=현장도착도; invstDeptNm=건축설비과; krnPrdctNm=보통합판, 1급, 18×1220×2440mm; nticeDt=2024-10-30 16:58:14; prce=17453; prceDiv=기타가격; prceNticeNo=R24CW21466454; unit=㎡; vatYnNm=부가가치세별도.",
      "hash": "sha256:e166371353077fa7c93154a2763a9bfd18242d390e8402a9aaaf412404e8aef8",
      "source_path": "backfill_price_info/raw/getPriceInfoListFcltyCmmnMtrilBildng/2026-05/page_00001.json"
    },
    {
      "source_line": 5736,
      "chunk_id": "chunk:g2b:sentence:e5bb75e8a1956a2b62e5715b",
      "evidence_id": "evidence:g2b:sentence:row:5ee8f53ecd41ed88551f4b56",
      "document_id": "doc:g2b:source:ef1b5d8a73bbeb6fd7080c7e",
      "service": "backfill_price_info",
      "operation": "getPriceInfoListFcltyCmmnMtrilBildng",
      "source_file": "backfill_price_info/raw/getPriceInfoListFcltyCmmnMtrilBildng/2026-05/page_00001.json",
      "text": "G2B public OpenAPI row. service=backfill_price_info. operation=getPriceInfoListFcltyCmmnMtrilBildng. source_file=raw/getPriceInfoListFcltyCmmnMtrilBildng/2026-05/page_00001.json. row_index=16. invstDeptTelNo=042-724-7109; invstOfclNm=이상대; prdctClsfcNo=11122001; prdctClsfcNoNm=보통합판; prdctIdntNo=20142414; splyJrsdctRgnNm=002; bsnsDivCd=포110002; bsnsDivNm=시설공통자재(건축); distbStep=수요자지정장소도; dlvryCndtnNm=현장도착도; invstDeptNm=건축설비과; krnPrdctNm=보통합판, 1급, 7.5×1220×2440mm; nticeDt=2024-10-30 16:58:14; prce=21291; prceDiv=기타가격; prceNticeNo=R24CW21466440; unit=매; vatYnNm=부가가치세별도.",
      "hash": "sha256:d36154499fb979f3213a822eb90289fff5dd93d645b06f3be6e6d2e8d133a5ff",
      "source_path": "backfill_price_info/raw/getPriceInfoListFcltyCmmnMtrilBildng/2026-05/page_00001.json"
    },
    {
      "source_line": 5737,
      "chunk_id": "chunk:g2b:sentence:b56d28d44b300a79b7313653",
      "evidence_id": "evidence:g2b:sentence:row:3aecc238f8cc275f03d800b0",
      "document_id": "doc:g2b:source:ef1b5d8a73bbeb6fd7080c7e",
      "service": "backfill_price_info",
      "operation": "getPriceInfoListFcltyCmmnMtrilBildng",
      "source_file": "backfill_price_info/raw/getPriceInfoListFcltyCmmnMtrilBildng/2026-05/page_00001.json",
      "text": "G2B public OpenAPI row. service=backfill_price_info. operation=getPriceInfoListFcltyCmmnMtrilBildng. source_file=raw/getPriceInfoListFcltyCmmnMtrilBildng/2026-05/page_00001.json. row_index=17. invstDeptTelNo=042-724-7109; invstOfclNm=이상대; prdctClsfcNo=11122001; prdctClsfcNoNm=보통합판; prdctIdntNo=20142411; splyJrsdctRgnNm=002; bsnsDivCd=포110002; bsnsDivNm=시설공통자재(건축); distbStep=수요자지정장소도; dlvryCndtnNm=현장도착도; invstDeptNm=건축설비과; krnPrdctNm=보통합판, 1급, 4.8×1220×2440mm; nticeDt=2024-10-30 16:58:14; prce=4316; prceDiv=기타가격; prceNticeNo=R24CW21466434; unit=㎡; vatYnNm=부가가치세별도.",
      "hash": "sha256:6ed2892d33981ffb4d9a083bdf3e9e7e62c99650108e8ed57123450afda57fa5",
      "source_path": "backfill_price_info/raw/getPriceInfoListFcltyCmmnMtrilBildng/2026-05/page_00001.json"
    },
    {
      "source_line": 5738,
      "chunk_id": "chunk:g2b:sentence:61d2fa43e8aa247f74f37ee6",
      "evidence_id": "evidence:g2b:sentence:row:cbc52a27816e4d5f9af1c6e8",
      "document_id": "doc:g2b:source:ef1b5d8a73bbeb6fd7080c7e",
      "service": "backfill_price_info",
      "operation": "getPriceInfoListFcltyCmmnMtrilBildng",
      "source_file": "backfill_price_info/raw/getPriceInfoListFcltyCmmnMtrilBildng/2026-05/page_00001.json",
      "text": "G2B public OpenAPI row. service=backfill_price_info. operation=getPriceInfoListFcltyCmmnMtrilBildng. source_file=raw/getPriceInfoListFcltyCmmnMtrilBildng/2026-05/page_00001.json. row_index=18. invstDeptTelNo=042-724-7109; invstOfclNm=이상대; prdctClsfcNo=11122001; prdctClsfcNoNm=보통합판; prdctIdntNo=20142410; splyJrsdctRgnNm=002; bsnsDivCd=포110002; bsnsDivNm=시설공통자재(건축); distbStep=수요자지정장소도; dlvryCndtnNm=현장도착도; invstDeptNm=건축설비과; krnPrdctNm=보통합판, 1급, 2.7×1220×2440mm; nticeDt=2024-10-30 16:58:14; prce=10812; prceDiv=기타가격; prceNticeNo=R24CW21466428; unit=매; vatYnNm=부가가치세별도.",
      "hash": "sha256:2a7faf73bb826ca5a42785cbd4bfa0b1054f6984c7ea8b34fb2a0527256b80de",
      "source_path": "backfill_price_info/raw/getPriceInfoListFcltyCmmnMtrilBildng/2026-05/page_00001.json"
    },
    {
      "source_line": 5739,
      "chunk_id": "chunk:g2b:sentence:23d366ac92af7b929e431414",
      "evidence_id": "evidence:g2b:sentence:row:3620292b57f2fe95cad5b247",
      "document_id": "doc:g2b:source:ef1b5d8a73bbeb6fd7080c7e",
      "service": "backfill_price_info",
      "operation": "getPriceInfoListFcltyCmmnMtrilBildng",
      "source_file": "backfill_price_info/raw/getPriceInfoListFcltyCmmnMtrilBildng/2026-05/page_00001.json",
      "text": "G2B public OpenAPI row. service=backfill_price_info. operation=getPriceInfoListFcltyCmmnMtrilBildng. source_file=raw/getPriceInfoListFcltyCmmnMtrilBildng/2026-05/page_00001.json. row_index=19. invstDeptTelNo=042-724-7109; invstOfclNm=이상대; prdctClsfcNo=11122001; prdctClsfcNoNm=보통합판; prdctIdntNo=20142420; splyJrsdctRgnNm=002; bsnsDivCd=포110002; bsnsDivNm=시설공통자재(건축); distbStep=수요자지정장소도; dlvryCndtnNm=현장도착도; invstDeptNm=건축설비과; krnPrdctNm=보통합판, 1급, 15×1220×2440mm; nticeDt=2024-10-30 16:58:14; prce=41469; prceDiv=기타가격; prceNticeNo=R24CW21466452; unit=매; vatYnNm=부가가치세별도.",
      "hash": "sha256:62d5dfc3a6507f6651973320827785d0927c8f77fbdb4e99a2f900c94e34f94b",
      "source_path": "backfill_price_info/raw/getPriceInfoListFcltyCmmnMtrilBildng/2026-05/page_00001.json"
    },
    {
      "source_line": 5740,
      "chunk_id": "chunk:g2b:sentence:7baa48d7e398541e1dc4e1ee",
      "evidence_id": "evidence:g2b:sentence:row:358f28b6c6d2d41715c87ff6",
      "document_id": "doc:g2b:source:ef1b5d8a73bbeb6fd7080c7e",
      "service": "backfill_price_info",
      "operation": "getPriceInfoListFcltyCmmnMtrilBildng",
      "source_file": "backfill_price_info/raw/getPriceInfoListFcltyCmmnMtrilBildng/2026-05/page_00001.json",
      "text": "G2B public OpenAPI row. service=backfill_price_info. operation=getPriceInfoListFcltyCmmnMtrilBildng. source_file=raw/getPriceInfoListFcltyCmmnMtrilBildng/2026-05/page_00001.json. row_index=20. invstDeptTelNo=042-724-7109; invstOfclNm=이상대; prdctClsfcNo=11122001; prdctClsfcNoNm=보통합판; prdctIdntNo=20142419; splyJrsdctRgnNm=002; bsnsDivCd=포110002; bsnsDivNm=시설공통자재(건축); distbStep=수요자지정장소도; dlvryCndtnNm=현장도착도; invstDeptNm=건축설비과; krnPrdctNm=보통합판, 1급, 15×1220×2440mm; nticeDt=2024-10-30 16:58:14; prce=13929; prceDiv=기타가격; prceNticeNo=R24CW21466450; unit=㎡; vatYnNm=부가가치세별도.",
      "hash": "sha256:aed3ffe58a8be515bfc508bf2c9563c6e4304ebb69c69893329313a03e654c88",
      "source_path": "backfill_price_info/raw/getPriceInfoListFcltyCmmnMtrilBildng/2026-05/page_00001.json"
    },
    {
      "source_line": 5741,
      "chunk_id": "chunk:g2b:sentence:fe1f656f2c38eaac0d9bdb09",
      "evidence_id": "evidence:g2b:sentence:row:276c1707defcd4a90a087fe4",
      "document_id": "doc:g2b:source:ef1b5d8a73bbeb6fd7080c7e",
      "service": "backfill_price_info",
      "operation": "getPriceInfoListFcltyCmmnMtrilBildng",
      "source_file": "backfill_price_info/raw/getPriceInfoListFcltyCmmnMtrilBildng/2026-05/page_00001.json",
      "text": "G2B public OpenAPI row. service=backfill_price_info. operation=getPriceInfoListFcltyCmmnMtrilBildng. source_file=raw/getPriceInfoListFcltyCmmnMtrilBildng/2026-05/page_00001.json. row_index=21. invstDeptTelNo=042-724-7109; invstOfclNm=이상대; prdctClsfcNo=11122001; prdctClsfcNoNm=보통합판; prdctIdntNo=20142416; splyJrsdctRgnNm=002; bsnsDivCd=포110002; bsnsDivNm=시설공통자재(건축); distbStep=수요자지정장소도; dlvryCndtnNm=현장도착도; invstDeptNm=건축설비과; krnPrdctNm=보통합판, 1급, 9.0×1220×2440mm; nticeDt=2024-10-30 16:58:14; prce=25364; prceDiv=기타가격; prceNticeNo=R24CW21466444; unit=매; vatYnNm=부가가치세별도.",
      "hash": "sha256:c3216fd9ad0b10019dc0aebf95a1009c54fde5cbb8cce6c0e844d5861738018a",
      "source_path": "backfill_price_info/raw/getPriceInfoListFcltyCmmnMtrilBildng/2026-05/page_00001.json"
    },
    {
      "source_line": 5742,
      "chunk_id": "chunk:g2b:sentence:d0456fcf78a6c778d16ad5ed",
      "evidence_id": "evidence:g2b:sentence:row:466e3676fc1b9db8be48562b",
      "document_id": "doc:g2b:source:ef1b5d8a73bbeb6fd7080c7e",
      "service": "backfill_price_info",
      "operation": "getPriceInfoListFcltyCmmnMtrilBildng",
      "source_file": "backfill_price_info/raw/getPriceInfoListFcltyCmmnMtrilBildng/2026-05/page_00001.json",
      "text": "G2B public OpenAPI row. service=backfill_price_info. operation=getPriceInfoListFcltyCmmnMtrilBildng. source_file=raw/getPriceInfoListFcltyCmmnMtrilBildng/2026-05/page_00001.json. row_index=22. invstDeptTelNo=042-724-7109; invstOfclNm=이상대; prdctClsfcNo=11122001; prdctClsfcNoNm=보통합판; prdctIdntNo=20142415; splyJrsdctRgnNm=002; bsnsDivCd=포110002; bsnsDivNm=시설공통자재(건축); distbStep=수요자지정장소도; dlvryCndtnNm=현장도착도; invstDeptNm=건축설비과; krnPrdctNm=보통합판, 1급, 9.0×1220×2440mm; nticeDt=2024-10-30 16:58:14; prce=8518; prceDiv=기타가격; prceNticeNo=R24CW21466442; unit=㎡; vatYnNm=부가가치세별도.",
      "hash": "sha256:6a2b6101d970eec134f7416a3cad1e7d8effb53bdb8f298f0348c325f9b48bdd",
      "source_path": "backfill_price_info/raw/getPriceInfoListFcltyCmmnMtrilBildng/2026-05/page_00001.json"
    },
    {
      "source_line": 5743,
      "chunk_id": "chunk:g2b:sentence:8c4f0a3e53c480dcb982056d",
      "evidence_id": "evidence:g2b:sentence:row:2ea0b3e0a7f726d5e961ef3f",
      "document_id": "doc:g2b:source:ef1b5d8a73bbeb6fd7080c7e",
      "service": "backfill_price_info",
      "operation": "getPriceInfoListFcltyCmmnMtrilBildng",
      "source_file": "backfill_price_info/raw/getPriceInfoListFcltyCmmnMtrilBildng/2026-05/page_00001.json",
      "text": "G2B public OpenAPI row. service=backfill_price_info. operation=getPriceInfoListFcltyCmmnMtrilBildng. source_file=raw/getPriceInfoListFcltyCmmnMtrilBildng/2026-05/page_00001.json. row_index=23. invstDeptTelNo=042-724-7109; invstOfclNm=이상대; prdctClsfcNo=11122001; prdctClsfcNoNm=보통합판; prdctIdntNo=20142409; splyJrsdctRgnNm=002; bsnsDivCd=포110002; bsnsDivNm=시설공통자재(건축); distbStep=수요자지정장소도; dlvryCndtnNm=현장도착도; invstDeptNm=건축설비과; krnPrdctNm=보통합판, 1급, 2.7×1220×2440mm; nticeDt=2024-10-30 16:58:14; prce=3632; prceDiv=기타가격; prceNticeNo=R24CW21466426; unit=㎡; vatYnNm=부가가치세별도.",
      "hash": "sha256:70a5de6ebc99453fa2498e2231aafd35adf962c97a285c0e2b04e14ebb37f869",
      "source_path": "backfill_price_info/raw/getPriceInfoListFcltyCmmnMtrilBildng/2026-05/page_00001.json"
    },
    {
      "source_line": 5744,
      "chunk_id": "chunk:g2b:sentence:f140efbaad257ffe11468cfe",
      "evidence_id": "evidence:g2b:sentence:row:c005c8255f8f22d6f6c229a4",
      "document_id": "doc:g2b:source:ef1b5d8a73bbeb6fd7080c7e",
      "service": "backfill_price_info",
      "operation": "getPriceInfoListFcltyCmmnMtrilBildng",
      "source_file": "backfill_price_info/raw/getPriceInfoListFcltyCmmnMtrilBildng/2026-05/page_00001.json",
      "text": "G2B public OpenAPI row. service=backfill_price_info. operation=getPriceInfoListFcltyCmmnMtrilBildng. source_file=raw/getPriceInfoListFcltyCmmnMtrilBildng/2026-05/page_00001.json. row_index=24. invstDeptTelNo=042-724-7109; invstOfclNm=이상대; prdctClsfcNo=11122001; prdctClsfcNoNm=보통합판; prdctIdntNo=20142418; splyJrsdctRgnNm=002; bsnsDivCd=포110002; bsnsDivNm=시설공통자재(건축); distbStep=수요자지정장소도; dlvryCndtnNm=현장도착도; invstDeptNm=건축설비과; krnPrdctNm=보통합판, 1급, 12×1220×2440mm; nticeDt=2024-10-30 16:58:14; prce=30878; prceDiv=기타가격; prceNticeNo=R24CW21466448; unit=매; vatYnNm=부가가치세별도.",
      "hash": "sha256:421123eda2ff07b16f995138251244e99cd8cb107ee32bd6d97c43eadd3243c0",
      "source_path": "backfill_price_info/raw/getPriceInfoListFcltyCmmnMtrilBildng/2026-05/page_00001.json"
    },
    {
      "source_line": 5745,
      "chunk_id": "chunk:g2b:sentence:86d98884abb44f221b8d938d",
      "evidence_id": "evidence:g2b:sentence:row:170cbe03b8085d0346d34196",
      "document_id": "doc:g2b:source:ef1b5d8a73bbeb6fd7080c7e",
      "service": "backfill_price_info",
      "operation": "getPriceInfoListFcltyCmmnMtrilBildng",
      "source_file": "backfill_price_info/raw/getPriceInfoListFcltyCmmnMtrilBildng/2026-05/page_00001.json",
      "text": "G2B public OpenAPI row. service=backfill_price_info. operation=getPriceInfoListFcltyCmmnMtrilBildng. source_file=raw/getPriceInfoListFcltyCmmnMtrilBildng/2026-05/page_00001.json. row_index=25. invstDeptTelNo=042-724-7109; invstOfclNm=이상대; prdctClsfcNo=11122001; prdctClsfcNoNm=보통합판; prdctIdntNo=20142413; splyJrsdctRgnNm=002; bsnsDivCd=포110002; bsnsDivNm=시설공통자재(건축); distbStep=수요자지정장소도; dlvryCndtnNm=현장도착도; invstDeptNm=건축설비과; krnPrdctNm=보통합판, 1급, 7.5×1220×2440mm; nticeDt=2024-10-30 16:58:14; prce=7152; prceDiv=기타가격; prceNticeNo=R24CW21466438; unit=㎡; vatYnNm=부가가치세별도.",
      "hash": "sha256:377ac0b55104710606fbeea0e3201ef758178731e968c7810dde678fbd2a59aa",
      "source_path": "backfill_price_info/raw/getPriceInfoListFcltyCmmnMtrilBildng/2026-05/page_00001.json"
    },
    {
      "source_line": 5746,
      "chunk_id": "chunk:g2b:sentence:872554e1bcf5c25f0e65850e",
      "evidence_id": "evidence:g2b:sentence:row:5bfce12ecf11b63725ff3e2c",
      "document_id": "doc:g2b:source:ef1b5d8a73bbeb6fd7080c7e",
      "service": "backfill_price_info",
      "operation": "getPriceInfoListFcltyCmmnMtrilBildng",
      "source_file": "backfill_price_info/raw/getPriceInfoListFcltyCmmnMtrilBildng/2026-05/page_00001.json",
      "text": "G2B public OpenAPI row. service=backfill_price_info. operation=getPriceInfoListFcltyCmmnMtrilBildng. source_file=raw/getPriceInfoListFcltyCmmnMtrilBildng/2026-05/page_00001.json. row_index=26. invstDeptTelNo=042-724-7109; invstOfclNm=이상대; prdctClsfcNo=11122001; prdctClsfcNoNm=보통합판; prdctIdntNo=20142412; splyJrsdctRgnNm=002; bsnsDivCd=포110002; bsnsDivNm=시설공통자재(건축); distbStep=수요자지정장소도; dlvryCndtnNm=현장도착도; invstDeptNm=건축설비과; krnPrdctNm=보통합판, 1급, 4.8×1220×2440mm; nticeDt=2024-10-30 16:58:14; prce=12858; prceDiv=기타가격; prceNticeNo=R24CW21466436; unit=매; vatYnNm=부가가치세별도.",
      "hash": "sha256:76ec652327f45bbe2a5293981656507b282c1a0d5140522710d7302ace844469",
      "source_path": "backfill_price_info/raw/getPriceInfoListFcltyCmmnMtrilBildng/2026-05/page_00001.json"
    },
    {
      "source_line": 5747,
      "chunk_id": "chunk:g2b:sentence:0e1a422746b66758f0f9f645",
      "evidence_id": "evidence:g2b:sentence:row:8fb46edb5c52827959988034",
      "document_id": "doc:g2b:source:ef1b5d8a73bbeb6fd7080c7e",
      "service": "backfill_price_info",
      "operation": "getPriceInfoListFcltyCmmnMtrilBildng",
      "source_file": "backfill_price_info/raw/getPriceInfoListFcltyCmmnMtrilBildng/2026-05/page_00001.json",
      "text": "G2B public OpenAPI row. service=backfill_price_info. operation=getPriceInfoListFcltyCmmnMtrilBildng. source_file=raw/getPriceInfoListFcltyCmmnMtrilBildng/2026-05/page_00001.json. row_index=27. invstDeptTelNo=042-724-7109; invstOfclNm=이상대; prdctClsfcNo=11122001; prdctClsfcNoNm=보통합판; prdctIdntNo=20935462; splyJrsdctRgnNm=002; bsnsDivCd=포110002; bsnsDivNm=시설공통자재(건축); distbStep=수요자지정장소도; dlvryCndtnNm=현장도착도; invstDeptNm=건축설비과; krnPrdctNm=보통합판, 보통합판, 1급, 3.6×1220×2440mm; nticeDt=2024-10-30 16:58:14; prce=12046; prceDiv=기타가격; prceNticeNo=R24CW21466432; unit=매; vatYnNm=부가가치세별도.",
      "hash": "sha256:997edff1b065977858422b7db4654ef035b3eaa21a0fa7e166f7898f17beb15b",
      "source_path": "backfill_price_info/raw/getPriceInfoListFcltyCmmnMtrilBildng/2026-05/page_00001.json"
    },
    {
      "source_line": 5748,
      "chunk_id": "chunk:g2b:sentence:56c6e3c1b5df6c962138f2a8",
      "evidence_id": "evidence:g2b:sentence:row:86023dce8a565379501f471d",
      "document_id": "doc:g2b:source:ef1b5d8a73bbeb6fd7080c7e",
      "service": "backfill_price_info",
      "operation": "getPriceInfoListFcltyCmmnMtrilBildng",
      "source_file": "backfill_price_info/raw/getPriceInfoListFcltyCmmnMtrilBildng/2026-05/page_00001.json",
      "text": "G2B public OpenAPI row. service=backfill_price_info. operation=getPriceInfoListFcltyCmmnMtrilBildng. source_file=raw/getPriceInfoListFcltyCmmnMtrilBildng/2026-05/page_00001.json. row_index=28. invstDeptTelNo=042-724-7109; invstOfclNm=이상대; prdctClsfcNo=11122001; prdctClsfcNoNm=치장합판; prdctIdntNo=20142448; splyJrsdctRgnNm=002; bsnsDivCd=포110002; bsnsDivNm=시설공통자재(건축); distbStep=수요자지정장소도; dlvryCndtnNm=현장도착도; invstDeptNm=건축설비과; krnPrdctNm=치장합판, 태고, 양면, 18×1220×2440mm; nticeDt=2024-10-30 17:03:07; prce=56249; prceDiv=기타가격; prceNticeNo=R24CW21468748; unit=매; vatYnNm=부가가치세별도.",
      "hash": "sha256:652ca699e495cce68940aa3c44745723800e7e7afed17239ce36555420ad54ac",
      "source_path": "backfill_price_info/raw/getPriceInfoListFcltyCmmnMtrilBildng/2026-05/page_00001.json"
    },
    {
      "source_line": 5749,
      "chunk_id": "chunk:g2b:sentence:af7758676573ad2914a46a0b",
      "evidence_id": "evidence:g2b:sentence:row:fa2839fb7387b22ec28941e9",
      "document_id": "doc:g2b:source:ef1b5d8a73bbeb6fd7080c7e",
      "service": "backfill_price_info",
      "operation": "getPriceInfoListFcltyCmmnMtrilBildng",
      "source_file": "backfill_price_info/raw/getPriceInfoListFcltyCmmnMtrilBildng/2026-05/page_00001.json",
      "text": "G2B public OpenAPI row. service=backfill_price_info. operation=getPriceInfoListFcltyCmmnMtrilBildng. source_file=raw/getPriceInfoListFcltyCmmnMtrilBildng/2026-05/page_00001.json. row_index=29. invstDeptTelNo=042-724-7109; invstOfclNm=이상대; prdctClsfcNo=11122001; prdctClsfcNoNm=치장합판; prdctIdntNo=20142443; splyJrsdctRgnNm=002; bsnsDivCd=포110002; bsnsDivNm=시설공통자재(건축); distbStep=수요자지정장소도; dlvryCndtnNm=현장도착도; invstDeptNm=건축설비과; krnPrdctNm=치장합판, 태고, 양면, 12×1220×2440mm; nticeDt=2024-10-30 17:03:07; prce=12385; prceDiv=기타가격; prceNticeNo=R24CW21468738; unit=㎡; vatYnNm=부가가치세별도.",
      "hash": "sha256:0d9d5b3b2cf0cc02d9facf85390c5ba83b8bacc53272cf4f28068676d0624522",
      "source_path": "backfill_price_info/raw/getPriceInfoListFcltyCmmnMtrilBildng/2026-05/page_00001.json"
    },
    {
      "source_line": 5750,
      "chunk_id": "chunk:g2b:sentence:ac7514f8b4e8e71dbcc00386",
      "evidence_id": "evidence:g2b:sentence:row:3aede6f0615d5d7461393940",
      "document_id": "doc:g2b:source:ef1b5d8a73bbeb6fd7080c7e",
      "service": "backfill_price_info",
      "operation": "getPriceInfoListFcltyCmmnMtrilBildng",
      "source_file": "backfill_price_info/raw/getPriceInfoListFcltyCmmnMtrilBildng/2026-05/page_00001.json",
      "text": "G2B public OpenAPI row. service=backfill_price_info. operation=getPriceInfoListFcltyCmmnMtrilBildng. source_file=raw/getPriceInfoListFcltyCmmnMtrilBildng/2026-05/page_00001.json. row_index=30. invstDeptTelNo=042-724-7109; invstOfclNm=이상대; prdctClsfcNo=11122001; prdctClsfcNoNm=치장합판; prdctIdntNo=20142445; splyJrsdctRgnNm=002; bsnsDivCd=포110002; bsnsDivNm=시설공통자재(건축); distbStep=수요자지정장소도; dlvryCndtnNm=현장도착도; invstDeptNm=건축설비과; krnPrdctNm=치장합판, 태고, 양면, 15×1220×2440mm; nticeDt=2024-10-30 17:03:07; prce=15624; prceDiv=기타가격; prceNticeNo=R24CW21468742; unit=㎡; vatYnNm=부가가치세별도.",
      "hash": "sha256:ce3636ef9d4673255a1d5f25121c83abd2280e5f3ab971ca308b18001ff2b908",
      "source_path": "backfill_price_info/raw/getPriceInfoListFcltyCmmnMtrilBildng/2026-05/page_00001.json"
    }
  ]
}
